{
"meta":{"test_sets":[],"test_metrics":[],"learn_metrics":[{"best_value":"Min","name":"RMSE"}],"launch_mode":"Train","parameters":"","iteration_count":1000,"learn_sets":["learn"],"name":"experiment"},
"iterations":[
{"learn":[14.81187677],"iteration":0,"passed_time":0.13493435,"remaining_time":134.7994157},
{"learn":[14.42555727],"iteration":1,"passed_time":0.1376066458,"remaining_time":68.66571627},
{"learn":[14.06817861],"iteration":2,"passed_time":0.1401428319,"remaining_time":46.57413448},
{"learn":[13.72601314],"iteration":3,"passed_time":0.1420423364,"remaining_time":35.36854176},
{"learn":[13.37266148],"iteration":4,"passed_time":0.1439034724,"remaining_time":28.636791},
{"learn":[13.05775076],"iteration":5,"passed_time":0.1455707045,"remaining_time":24.11621338},
{"learn":[12.77327823],"iteration":6,"passed_time":0.1471750775,"remaining_time":20.877836},
{"learn":[12.46120265],"iteration":7,"passed_time":0.1486348301,"remaining_time":18.43071894},
{"learn":[12.19967481],"iteration":8,"passed_time":0.1502654069,"remaining_time":16.54589092},
{"learn":[11.89911564],"iteration":9,"passed_time":0.1523727221,"remaining_time":15.08489949},
{"learn":[11.60372835],"iteration":10,"passed_time":0.1536382182,"remaining_time":13.81347252},
{"learn":[11.36862641],"iteration":11,"passed_time":0.1545554886,"remaining_time":12.72506856},
{"learn":[11.15443322],"iteration":12,"passed_time":0.1556479396,"remaining_time":11.81727049},
{"learn":[10.94476672],"iteration":13,"passed_time":0.1567757549,"remaining_time":11.04149245},
{"learn":[10.70419099],"iteration":14,"passed_time":0.1576232595,"remaining_time":10.35059404},
{"learn":[10.47157818],"iteration":15,"passed_time":0.1583762755,"remaining_time":9.740140941},
{"learn":[10.25640413],"iteration":16,"passed_time":0.1590686387,"remaining_time":9.19791011},
{"learn":[10.05094896],"iteration":17,"passed_time":0.1597900819,"remaining_time":8.717436692},
{"learn":[9.852281775],"iteration":18,"passed_time":0.1606249783,"remaining_time":8.293321248},
{"learn":[9.653774855],"iteration":19,"passed_time":0.1616012313,"remaining_time":7.918460333},
{"learn":[9.501485114],"iteration":20,"passed_time":0.1631934001,"remaining_time":7.607920892},
{"learn":[9.321604979],"iteration":21,"passed_time":0.1642825161,"remaining_time":7.303104579},
{"learn":[9.137156358],"iteration":22,"passed_time":0.1650115623,"remaining_time":7.00940419},
{"learn":[8.973164893],"iteration":23,"passed_time":0.1656836803,"remaining_time":6.737802998},
{"learn":[8.832393626],"iteration":24,"passed_time":0.1664983976,"remaining_time":6.493437507},
{"learn":[8.691335295],"iteration":25,"passed_time":0.1672250785,"remaining_time":6.26450871},
{"learn":[8.551538746],"iteration":26,"passed_time":0.1679337821,"remaining_time":6.051835927},
{"learn":[8.412619329],"iteration":27,"passed_time":0.1685855656,"remaining_time":5.852327492},
{"learn":[8.273323828],"iteration":28,"passed_time":0.1692356743,"remaining_time":5.666477232},
{"learn":[8.146216263],"iteration":29,"passed_time":0.1699004665,"remaining_time":5.493448418},
{"learn":[8.025759104],"iteration":30,"passed_time":0.1704869536,"remaining_time":5.329092194},
{"learn":[7.914797332],"iteration":31,"passed_time":0.1711347034,"remaining_time":5.176824779},
{"learn":[7.822029751],"iteration":32,"passed_time":0.1717601074,"remaining_time":5.033091631},
{"learn":[7.710016847],"iteration":33,"passed_time":0.1724883083,"remaining_time":4.90069723},
{"learn":[7.602856605],"iteration":34,"passed_time":0.1733480416,"remaining_time":4.779453146},
{"learn":[7.504978034],"iteration":35,"passed_time":0.1742992348,"remaining_time":4.667346175},
{"learn":[7.407123395],"iteration":36,"passed_time":0.1764498298,"remaining_time":4.59246449},
{"learn":[7.330586933],"iteration":37,"passed_time":0.1771187545,"remaining_time":4.4839011},
{"learn":[7.239309831],"iteration":38,"passed_time":0.1778251989,"remaining_time":4.381795286},
{"learn":[7.15456849],"iteration":39,"passed_time":0.1785560727,"remaining_time":4.285345745},
{"learn":[7.077710121],"iteration":40,"passed_time":0.179281597,"remaining_time":4.19344028},
{"learn":[7.010781572],"iteration":41,"passed_time":0.1799681144,"remaining_time":4.10498699},
{"learn":[6.931484818],"iteration":42,"passed_time":0.1806286027,"remaining_time":4.020036575},
{"learn":[6.869087401],"iteration":43,"passed_time":0.1813073374,"remaining_time":3.939313968},
{"learn":[6.80042605],"iteration":44,"passed_time":0.1819312527,"remaining_time":3.860985474},
{"learn":[6.742542215],"iteration":45,"passed_time":0.1825677249,"remaining_time":3.786295859},
{"learn":[6.673260026],"iteration":46,"passed_time":0.1831553467,"remaining_time":3.713766923},
{"learn":[6.615368866],"iteration":47,"passed_time":0.1837969922,"remaining_time":3.645307011},
{"learn":[6.553323094],"iteration":48,"passed_time":0.18442013,"remaining_time":3.579255992},
{"learn":[6.495770633],"iteration":49,"passed_time":0.1851054406,"remaining_time":3.517003371},
{"learn":[6.44987694],"iteration":50,"passed_time":0.1859329304,"remaining_time":3.459810804},
{"learn":[6.401519521],"iteration":51,"passed_time":0.186906275,"remaining_time":3.407445168},
{"learn":[6.349427946],"iteration":52,"passed_time":0.188630371,"remaining_time":3.370433233},
{"learn":[6.303639269],"iteration":53,"passed_time":0.1894863128,"remaining_time":3.319519479},
{"learn":[6.25716495],"iteration":54,"passed_time":0.1901972622,"remaining_time":3.267934778},
{"learn":[6.213822599],"iteration":55,"passed_time":0.1909306254,"remaining_time":3.218544828},
{"learn":[6.174325681],"iteration":56,"passed_time":0.19162818,"remaining_time":3.170269715},
{"learn":[6.139347441],"iteration":57,"passed_time":0.1922736802,"remaining_time":3.122789772},
{"learn":[6.101029721],"iteration":58,"passed_time":0.192920113,"remaining_time":3.076912311},
{"learn":[6.067216836],"iteration":59,"passed_time":0.1935970014,"remaining_time":3.033019689},
{"learn":[6.0299242],"iteration":60,"passed_time":0.1942104268,"remaining_time":2.989567061},
{"learn":[5.996527138],"iteration":61,"passed_time":0.1948470364,"remaining_time":2.947847099},
{"learn":[5.96430137],"iteration":62,"passed_time":0.1954692884,"remaining_time":2.907217829},
{"learn":[5.929765249],"iteration":63,"passed_time":0.1960795514,"remaining_time":2.86766344},
{"learn":[5.899122572],"iteration":64,"passed_time":0.1967079158,"remaining_time":2.829567712},
{"learn":[5.872123844],"iteration":65,"passed_time":0.1975607711,"remaining_time":2.795784245},
{"learn":[5.843614466],"iteration":66,"passed_time":0.1985378857,"remaining_time":2.76471414},
{"learn":[5.816947636],"iteration":67,"passed_time":0.2000972023,"remaining_time":2.742508713},
{"learn":[5.800727042],"iteration":68,"passed_time":0.2009465926,"remaining_time":2.711322866},
{"learn":[5.776468068],"iteration":69,"passed_time":0.2016063012,"remaining_time":2.678483716},
{"learn":[5.7492616],"iteration":70,"passed_time":0.2022066342,"remaining_time":2.64577413},
{"learn":[5.72452714],"iteration":71,"passed_time":0.202860891,"remaining_time":2.614651484},
{"learn":[5.703930027],"iteration":72,"passed_time":0.2034706504,"remaining_time":2.583798533},
{"learn":[5.682515856],"iteration":73,"passed_time":0.2040556407,"remaining_time":2.553453018},
{"learn":[5.661949722],"iteration":74,"passed_time":0.2047349757,"remaining_time":2.5250647},
{"learn":[5.640022714],"iteration":75,"passed_time":0.2054111131,"remaining_time":2.49736669},
{"learn":[5.621566138],"iteration":76,"passed_time":0.2059935776,"remaining_time":2.46924769},
{"learn":[5.603702791],"iteration":77,"passed_time":0.2066032696,"remaining_time":2.442156597},
{"learn":[5.58546367],"iteration":78,"passed_time":0.2071950219,"remaining_time":2.415526775},
{"learn":[5.564965512],"iteration":79,"passed_time":0.2077671869,"remaining_time":2.389322649},
{"learn":[5.549236154],"iteration":80,"passed_time":0.2083876836,"remaining_time":2.364299769},
{"learn":[5.536120535],"iteration":81,"passed_time":0.2091031887,"remaining_time":2.340935698},
{"learn":[5.520204601],"iteration":82,"passed_time":0.2099856241,"remaining_time":2.319961654},
{"learn":[5.499610861],"iteration":83,"passed_time":0.2112972486,"remaining_time":2.304146187},
{"learn":[5.479652311],"iteration":84,"passed_time":0.2128267035,"remaining_time":2.291016867},
{"learn":[5.460237658],"iteration":85,"passed_time":0.2134632656,"remaining_time":2.26866773},
{"learn":[5.445035106],"iteration":86,"passed_time":0.2140916331,"remaining_time":2.246731736},
{"learn":[5.43317717],"iteration":87,"passed_time":0.2147271895,"remaining_time":2.225354509},
{"learn":[5.42112736],"iteration":88,"passed_time":0.2154164808,"remaining_time":2.204993416},
{"learn":[5.409684974],"iteration":89,"passed_time":0.216085024,"remaining_time":2.184859688},
{"learn":[5.39921064],"iteration":90,"passed_time":0.2166288226,"remaining_time":2.163907689},
{"learn":[5.387823857],"iteration":91,"passed_time":0.2172601758,"remaining_time":2.144263474},
{"learn":[5.379957651],"iteration":92,"passed_time":0.2179507145,"remaining_time":2.125605355},
{"learn":[5.370864306],"iteration":93,"passed_time":0.2186245724,"remaining_time":2.107168751},
{"learn":[5.361475726],"iteration":94,"passed_time":0.2192808907,"remaining_time":2.088939012},
{"learn":[5.351778054],"iteration":95,"passed_time":0.2200089576,"remaining_time":2.071751018},
{"learn":[5.34132973],"iteration":96,"passed_time":0.2206934862,"remaining_time":2.054497093},
{"learn":[5.330229698],"iteration":97,"passed_time":0.2213993672,"remaining_time":2.037777849},
{"learn":[5.320899585],"iteration":98,"passed_time":0.2222404584,"remaining_time":2.022612657},
{"learn":[5.311319842],"iteration":99,"passed_time":0.2236208093,"remaining_time":2.012587284},
{"learn":[5.302114276],"iteration":100,"passed_time":0.2249794979,"remaining_time":2.002540283},
{"learn":[5.292270591],"iteration":101,"passed_time":0.2256291749,"remaining_time":1.98642156},
{"learn":[5.282089168],"iteration":102,"passed_time":0.226207684,"remaining_time":1.969983423},
{"learn":[5.275809129],"iteration":103,"passed_time":0.226809901,"remaining_time":1.954054532},
{"learn":[5.266958227],"iteration":104,"passed_time":0.227452543,"remaining_time":1.938762152},
{"learn":[5.257976744],"iteration":105,"passed_time":0.228080789,"remaining_time":1.923624768},
{"learn":[5.248035297],"iteration":106,"passed_time":0.2286932163,"remaining_time":1.908626562},
{"learn":[5.242979275],"iteration":107,"passed_time":0.2293413829,"remaining_time":1.89418994},
{"learn":[5.236558394],"iteration":108,"passed_time":0.2299871148,"remaining_time":1.879986416},
{"learn":[5.229693731],"iteration":109,"passed_time":0.2306205361,"remaining_time":1.865929792},
{"learn":[5.22806376],"iteration":110,"passed_time":0.2309058819,"remaining_time":1.849327289},
{"learn":[5.22115977],"iteration":111,"passed_time":0.2314879696,"remaining_time":1.835368902},
{"learn":[5.215102998],"iteration":112,"passed_time":0.2321013866,"remaining_time":1.821893185},
{"learn":[5.207924143],"iteration":113,"passed_time":0.2327162952,"remaining_time":1.808654715},
{"learn":[5.202432778],"iteration":114,"passed_time":0.2338507909,"remaining_time":1.799634347},
{"learn":[5.195690271],"iteration":115,"passed_time":0.2350463763,"remaining_time":1.791215489},
{"learn":[5.189053499],"iteration":116,"passed_time":0.2370372511,"remaining_time":1.78892216},
{"learn":[5.185074178],"iteration":117,"passed_time":0.2377440279,"remaining_time":1.77703587},
{"learn":[5.181879961],"iteration":118,"passed_time":0.2381780381,"remaining_time":1.76331808},
{"learn":[5.174019434],"iteration":119,"passed_time":0.2387604364,"remaining_time":1.750909867},
{"learn":[5.165632675],"iteration":120,"passed_time":0.2394045261,"remaining_time":1.739145276},
{"learn":[5.161030537],"iteration":121,"passed_time":0.2399746432,"remaining_time":1.727030629},
{"learn":[5.154351629],"iteration":122,"passed_time":0.2405899,"remaining_time":1.715425547},
{"learn":[5.151504583],"iteration":123,"passed_time":0.2412177301,"remaining_time":1.704086545},
{"learn":[5.14435685],"iteration":124,"passed_time":0.2418720317,"remaining_time":1.693104222},
{"learn":[5.136614967],"iteration":125,"passed_time":0.2424973468,"remaining_time":1.68208477},
{"learn":[5.128820577],"iteration":126,"passed_time":0.2431341004,"remaining_time":1.671307635},
{"learn":[5.122040361],"iteration":127,"passed_time":0.2437546021,"remaining_time":1.660578227},
{"learn":[5.116062397],"iteration":128,"passed_time":0.2443921206,"remaining_time":1.650120442},
{"learn":[5.111385171],"iteration":129,"passed_time":0.2450526154,"remaining_time":1.639967503},
{"learn":[5.10774503],"iteration":130,"passed_time":0.2458361613,"remaining_time":1.630775757},
{"learn":[5.100726601],"iteration":131,"passed_time":0.2468630987,"remaining_time":1.623311892},
{"learn":[5.094759033],"iteration":132,"passed_time":0.2481624141,"remaining_time":1.617720399},
{"learn":[5.084806232],"iteration":133,"passed_time":0.2493595909,"remaining_time":1.611532878},
{"learn":[5.074210657],"iteration":134,"passed_time":0.2500242843,"remaining_time":1.602007451},
{"learn":[5.070223645],"iteration":135,"passed_time":0.2506083708,"remaining_time":1.592100238},
{"learn":[5.065875884],"iteration":136,"passed_time":0.2512869589,"remaining_time":1.58292442},
{"learn":[5.062240377],"iteration":137,"passed_time":0.2519139273,"remaining_time":1.573549314},
{"learn":[5.0585536],"iteration":138,"passed_time":0.2525169022,"remaining_time":1.564151459},
{"learn":[5.051176038],"iteration":139,"passed_time":0.2531782817,"remaining_time":1.555238016},
{"learn":[5.045045531],"iteration":140,"passed_time":0.2538218325,"remaining_time":1.546333008},
{"learn":[5.0393909],"iteration":141,"passed_time":0.254495001,"remaining_time":1.537723316},
{"learn":[5.032813942],"iteration":142,"passed_time":0.2551112378,"remaining_time":1.528883432},
{"learn":[5.02902199],"iteration":143,"passed_time":0.2557750765,"remaining_time":1.520440732},
{"learn":[5.024543771],"iteration":144,"passed_time":0.2564166136,"remaining_time":1.511973825},
{"learn":[5.020428251],"iteration":145,"passed_time":0.2572957737,"remaining_time":1.505004046},
{"learn":[5.017891171],"iteration":146,"passed_time":0.2581966379,"remaining_time":1.498243075},
{"learn":[5.01415882],"iteration":147,"passed_time":0.2593611154,"remaining_time":1.493078854},
{"learn":[5.007461475],"iteration":148,"passed_time":0.2612567996,"remaining_time":1.49214454},
{"learn":[5.003516268],"iteration":149,"passed_time":0.2619830646,"remaining_time":1.484570699},
{"learn":[4.999753632],"iteration":150,"passed_time":0.2626567459,"remaining_time":1.476791902},
{"learn":[4.9965988],"iteration":151,"passed_time":0.263265752,"remaining_time":1.468745774},
{"learn":[4.989081409],"iteration":152,"passed_time":0.2638871694,"remaining_time":1.460865572},
{"learn":[4.983370019],"iteration":153,"passed_time":0.2644651404,"remaining_time":1.452840966},
{"learn":[4.980928261],"iteration":154,"passed_time":0.2650643567,"remaining_time":1.445028267},
{"learn":[4.977360588],"iteration":155,"passed_time":0.2657348026,"remaining_time":1.437693419},
{"learn":[4.974588182],"iteration":156,"passed_time":0.2664023546,"remaining_time":1.43042793},
{"learn":[4.970844297],"iteration":157,"passed_time":0.2670138371,"remaining_time":1.422947157},
{"learn":[4.96272654],"iteration":158,"passed_time":0.2676600788,"remaining_time":1.415736643},
{"learn":[4.958853834],"iteration":159,"passed_time":0.2682509467,"remaining_time":1.40831747},
{"learn":[4.958002296],"iteration":160,"passed_time":0.2686945253,"remaining_time":1.40021557},
{"learn":[4.955220921],"iteration":161,"passed_time":0.2693955383,"remaining_time":1.393539883},
{"learn":[4.951675631],"iteration":162,"passed_time":0.2701430244,"remaining_time":1.387176144},
{"learn":[4.948553295],"iteration":163,"passed_time":0.2710983542,"remaining_time":1.381940391},
{"learn":[4.947623712],"iteration":164,"passed_time":0.2722113162,"remaining_time":1.377554237},
{"learn":[4.947317717],"iteration":165,"passed_time":0.2733700517,"remaining_time":1.373437489},
{"learn":[4.943537108],"iteration":166,"passed_time":0.2740403613,"remaining_time":1.366919886},
{"learn":[4.937657052],"iteration":167,"passed_time":0.2746836184,"remaining_time":1.36033792},
{"learn":[4.93319074],"iteration":168,"passed_time":0.2753331706,"remaining_time":1.353857188},
{"learn":[4.930704901],"iteration":169,"passed_time":0.2759374276,"remaining_time":1.347223911},
{"learn":[4.926625583],"iteration":170,"passed_time":0.276565275,"remaining_time":1.340775514},
{"learn":[4.920222045],"iteration":171,"passed_time":0.2772000498,"remaining_time":1.334428147},
{"learn":[4.912927951],"iteration":172,"passed_time":0.2778654004,"remaining_time":1.328292984},
{"learn":[4.907666291],"iteration":173,"passed_time":0.2785063707,"remaining_time":1.322104955},
{"learn":[4.903006818],"iteration":174,"passed_time":0.2791695594,"remaining_time":1.316085066},
{"learn":[4.899129261],"iteration":175,"passed_time":0.2797989525,"remaining_time":1.309967823},
{"learn":[4.896425597],"iteration":176,"passed_time":0.2804102561,"remaining_time":1.303828479},
{"learn":[4.891770041],"iteration":177,"passed_time":0.2811295902,"remaining_time":1.29825013},
{"learn":[4.887737156],"iteration":178,"passed_time":0.2817959079,"remaining_time":1.292482907},
{"learn":[4.883246873],"iteration":179,"passed_time":0.2826174205,"remaining_time":1.28747936},
{"learn":[4.87975169],"iteration":180,"passed_time":0.2840946457,"remaining_time":1.285489032},
{"learn":[4.876092503],"iteration":181,"passed_time":0.2859564729,"remaining_time":1.285232939},
{"learn":[4.870606644],"iteration":182,"passed_time":0.2866562354,"remaining_time":1.279771281},
{"learn":[4.867559946],"iteration":183,"passed_time":0.2873698068,"remaining_time":1.274422621},
{"learn":[4.865480775],"iteration":184,"passed_time":0.2881294599,"remaining_time":1.26932708},
{"learn":[4.861467503],"iteration":185,"passed_time":0.2888281225,"remaining_time":1.264011246},
{"learn":[4.857895348],"iteration":186,"passed_time":0.2894598514,"remaining_time":1.258453792},
{"learn":[4.851554237],"iteration":187,"passed_time":0.2901622331,"remaining_time":1.2532539},
{"learn":[4.845698905],"iteration":188,"passed_time":0.2908402567,"remaining_time":1.24799708},
{"learn":[4.84101964],"iteration":189,"passed_time":0.2914963897,"remaining_time":1.242695135},
{"learn":[4.838291839],"iteration":190,"passed_time":0.2921635143,"remaining_time":1.237488393},
{"learn":[4.835654447],"iteration":191,"passed_time":0.293246416,"remaining_time":1.234078667},
{"learn":[4.829637438],"iteration":192,"passed_time":0.2942244437,"remaining_time":1.230254539},
{"learn":[4.827327632],"iteration":193,"passed_time":0.2950886085,"remaining_time":1.225986693},
{"learn":[4.823136863],"iteration":194,"passed_time":0.2962464738,"remaining_time":1.222966212},
{"learn":[4.821656816],"iteration":195,"passed_time":0.2983577897,"remaining_time":1.223875831},
{"learn":[4.818704409],"iteration":196,"passed_time":0.2993604528,"remaining_time":1.220235754},
{"learn":[4.812511577],"iteration":197,"passed_time":0.3002138703,"remaining_time":1.216017798},
{"learn":[4.807849408],"iteration":198,"passed_time":0.3010998797,"remaining_time":1.211964842},
{"learn":[4.80316738],"iteration":199,"passed_time":0.3018640512,"remaining_time":1.207456205},
{"learn":[4.796985485],"iteration":200,"passed_time":0.302766072,"remaining_time":1.203532794},
{"learn":[4.789889199],"iteration":201,"passed_time":0.3035809533,"remaining_time":1.199295053},
{"learn":[4.786562674],"iteration":202,"passed_time":0.3043526409,"remaining_time":1.194921452},
{"learn":[4.783378875],"iteration":203,"passed_time":0.3056569209,"remaining_time":1.192661319},
{"learn":[4.776769441],"iteration":204,"passed_time":0.3062912637,"remaining_time":1.187812462},
{"learn":[4.772849366],"iteration":205,"passed_time":0.3070526724,"remaining_time":1.183494281},
{"learn":[4.769587667],"iteration":206,"passed_time":0.3087896079,"remaining_time":1.182947628},
{"learn":[4.768445072],"iteration":207,"passed_time":0.3110873388,"remaining_time":1.184524867},
{"learn":[4.763689148],"iteration":208,"passed_time":0.3119170258,"remaining_time":1.180508935},
{"learn":[4.760687448],"iteration":209,"passed_time":0.3127315394,"remaining_time":1.176466267},
{"learn":[4.759443398],"iteration":210,"passed_time":0.3135817996,"remaining_time":1.172587867},
{"learn":[4.754218825],"iteration":211,"passed_time":0.3141989104,"remaining_time":1.167871422},
{"learn":[4.74827523],"iteration":212,"passed_time":0.3150164097,"remaining_time":1.163933871},
{"learn":[4.748150158],"iteration":213,"passed_time":0.3154317689,"remaining_time":1.15854846},
{"learn":[4.746667794],"iteration":214,"passed_time":0.3163087368,"remaining_time":1.15489469},
{"learn":[4.744567665],"iteration":215,"passed_time":0.3170444151,"remaining_time":1.150753803},
{"learn":[4.738486494],"iteration":216,"passed_time":0.317736125,"remaining_time":1.146485649},
{"learn":[4.736811893],"iteration":217,"passed_time":0.3185433769,"remaining_time":1.142664774},
{"learn":[4.734391264],"iteration":218,"passed_time":0.319428878,"remaining_time":1.139150474},
{"learn":[4.729773705],"iteration":219,"passed_time":0.3204711356,"remaining_time":1.136215844},
{"learn":[4.723734794],"iteration":220,"passed_time":0.3217794687,"remaining_time":1.134236227},
{"learn":[4.717262053],"iteration":221,"passed_time":0.3236227795,"remaining_time":1.134137488},
{"learn":[4.711270219],"iteration":222,"passed_time":0.3244060225,"remaining_time":1.130329504},
{"learn":[4.707011894],"iteration":223,"passed_time":0.3251230384,"remaining_time":1.126319097},
{"learn":[4.704135242],"iteration":224,"passed_time":0.3258434399,"remaining_time":1.122349626},
{"learn":[4.700384906],"iteration":225,"passed_time":0.3265515981,"remaining_time":1.118366978},
{"learn":[4.695880276],"iteration":226,"passed_time":0.3272632684,"remaining_time":1.114425139},
{"learn":[4.688295562],"iteration":227,"passed_time":0.3280589384,"remaining_time":1.110796055},
{"learn":[4.683475833],"iteration":228,"passed_time":0.3287832735,"remaining_time":1.106951545},
{"learn":[4.678973825],"iteration":229,"passed_time":0.3296326957,"remaining_time":1.103552938},
{"learn":[4.676282447],"iteration":230,"passed_time":0.3303830002,"remaining_time":1.099846438},
{"learn":[4.671193938],"iteration":231,"passed_time":0.3312158541,"remaining_time":1.096438689},
{"learn":[4.669294485],"iteration":232,"passed_time":0.332135949,"remaining_time":1.093340227},
{"learn":[4.66746135],"iteration":233,"passed_time":0.3331926883,"remaining_time":1.090707689},
{"learn":[4.665141601],"iteration":234,"passed_time":0.3349015374,"remaining_time":1.090211388},
{"learn":[4.660400289],"iteration":235,"passed_time":0.3358070977,"remaining_time":1.087104333},
{"learn":[4.657893131],"iteration":236,"passed_time":0.3364983572,"remaining_time":1.083325935},
{"learn":[4.653671826],"iteration":237,"passed_time":0.3372597115,"remaining_time":1.0797979},
{"learn":[4.649774185],"iteration":238,"passed_time":0.3381065328,"remaining_time":1.076565153},
{"learn":[4.647780888],"iteration":239,"passed_time":0.3388020936,"remaining_time":1.072873296},
{"learn":[4.644684249],"iteration":240,"passed_time":0.339528737,"remaining_time":1.069304197},
{"learn":[4.639592014],"iteration":241,"passed_time":0.3404415977,"remaining_time":1.066341864},
{"learn":[4.634603882],"iteration":242,"passed_time":0.3411352428,"remaining_time":1.062713493},
{"learn":[4.628803521],"iteration":243,"passed_time":0.3420128511,"remaining_time":1.059679162},
{"learn":[4.626519313],"iteration":244,"passed_time":0.3427668594,"remaining_time":1.056281546},
{"learn":[4.623650933],"iteration":245,"passed_time":0.343672252,"remaining_time":1.053369423},
{"learn":[4.620813242],"iteration":246,"passed_time":0.3450525163,"remaining_time":1.051921234},
{"learn":[4.616549716],"iteration":247,"passed_time":0.3467124281,"remaining_time":1.051321556},
{"learn":[4.611118618],"iteration":248,"passed_time":0.3479690316,"remaining_time":1.049496959},
{"learn":[4.605508331],"iteration":249,"passed_time":0.3488613511,"remaining_time":1.046584053},
{"learn":[4.600332727],"iteration":250,"passed_time":0.3498005458,"remaining_time":1.043827127},
{"learn":[4.598588228],"iteration":251,"passed_time":0.3504006662,"remaining_time":1.040078168},
{"learn":[4.595138173],"iteration":252,"passed_time":0.3513175204,"remaining_time":1.037289279},
{"learn":[4.594797132],"iteration":253,"passed_time":0.3521033929,"remaining_time":1.034130437},
{"learn":[4.591603857],"iteration":254,"passed_time":0.3548114108,"remaining_time":1.036605886},
{"learn":[4.586605708],"iteration":255,"passed_time":0.3556648868,"remaining_time":1.033651077},
{"learn":[4.581639967],"iteration":256,"passed_time":0.3567731903,"remaining_time":1.03144934},
{"learn":[4.577413582],"iteration":257,"passed_time":0.3582653931,"remaining_time":1.030360162},
{"learn":[4.571353623],"iteration":258,"passed_time":0.3596680582,"remaining_time":1.029011703},
{"learn":[4.566576691],"iteration":259,"passed_time":0.3604683861,"remaining_time":1.025948483},
{"learn":[4.561032097],"iteration":260,"passed_time":0.3612012893,"remaining_time":1.022711697},
{"learn":[4.558102162],"iteration":261,"passed_time":0.3620355633,"remaining_time":1.019779564},
{"learn":[4.553353577],"iteration":262,"passed_time":0.3629955502,"remaining_time":1.017215667},
{"learn":[4.546519004],"iteration":263,"passed_time":0.3637669245,"remaining_time":1.014138093},
{"learn":[4.538993155],"iteration":264,"passed_time":0.3646352029,"remaining_time":1.011346695},
{"learn":[4.535134422],"iteration":265,"passed_time":0.3655300324,"remaining_time":1.008643022},
{"learn":[4.533408391],"iteration":266,"passed_time":0.3663443687,"remaining_time":1.005731919},
{"learn":[4.531330071],"iteration":267,"passed_time":0.3671337586,"remaining_time":1.002768326},
{"learn":[4.529027846],"iteration":268,"passed_time":0.3679085173,"remaining_time":0.9997811382},
{"learn":[4.523172087],"iteration":269,"passed_time":0.3689783187,"remaining_time":0.9976080467},
{"learn":[4.520635102],"iteration":270,"passed_time":0.3706416853,"remaining_time":0.9970398103},
{"learn":[4.519350944],"iteration":271,"passed_time":0.3722433824,"remaining_time":0.9962984648},
{"learn":[4.515202225],"iteration":272,"passed_time":0.3733350123,"remaining_time":0.9941925053},
{"learn":[4.509762496],"iteration":273,"passed_time":0.3742288644,"remaining_time":0.9915699108},
{"learn":[4.507147067],"iteration":274,"passed_time":0.3748967837,"remaining_time":0.9883642481},
{"learn":[4.503919197],"iteration":275,"passed_time":0.375570452,"remaining_time":0.9851920553},
{"learn":[4.502092019],"iteration":276,"passed_time":0.3763148547,"remaining_time":0.982222527},
{"learn":[4.495921832],"iteration":277,"passed_time":0.3770046654,"remaining_time":0.9791272245},
{"learn":[4.49173105],"iteration":278,"passed_time":0.3776943907,"remaining_time":0.9760489451},
{"learn":[4.487219575],"iteration":279,"passed_time":0.3784159476,"remaining_time":0.9730695796},
{"learn":[4.482432905],"iteration":280,"passed_time":0.3792574474,"remaining_time":0.9704131839},
{"learn":[4.481018025],"iteration":281,"passed_time":0.3800524392,"remaining_time":0.9676512458},
{"learn":[4.475381098],"iteration":282,"passed_time":0.3809890346,"remaining_time":0.965261971},
{"learn":[4.474006907],"iteration":283,"passed_time":0.3825198755,"remaining_time":0.9643810945},
{"learn":[4.468761087],"iteration":284,"passed_time":0.3839267319,"remaining_time":0.9631846082},
{"learn":[4.464816839],"iteration":285,"passed_time":0.3848342949,"remaining_time":0.9607401627},
{"learn":[4.462086328],"iteration":286,"passed_time":0.3857630939,"remaining_time":0.9583591844},
{"learn":[4.457235883],"iteration":287,"passed_time":0.3864676483,"remaining_time":0.9554339082},
{"learn":[4.454231237],"iteration":288,"passed_time":0.387268569,"remaining_time":0.9527610815},
{"learn":[4.449797111],"iteration":289,"passed_time":0.387983467,"remaining_time":0.9498905572},
{"learn":[4.446382575],"iteration":290,"passed_time":0.3887412673,"remaining_time":0.9471393762},
{"learn":[4.44344693],"iteration":291,"passed_time":0.3895007576,"remaining_time":0.9444059465},
{"learn":[4.441611072],"iteration":292,"passed_time":0.3901742907,"remaining_time":0.9414785786},
{"learn":[4.439522416],"iteration":293,"passed_time":0.3908998636,"remaining_time":0.9386915092},
{"learn":[4.43827183],"iteration":294,"passed_time":0.3916805774,"remaining_time":0.9360501934},
{"learn":[4.434800734],"iteration":295,"passed_time":0.3925740496,"remaining_time":0.9336896314},
{"learn":[4.433088787],"iteration":296,"passed_time":0.3938001013,"remaining_time":0.9321261658},
{"learn":[4.427468348],"iteration":297,"passed_time":0.4105575714,"remaining_time":0.9671523996},
{"learn":[4.422984275],"iteration":298,"passed_time":0.411419745,"remaining_time":0.9645660242},
{"learn":[4.418164819],"iteration":299,"passed_time":0.4133538535,"remaining_time":0.9644923249},
{"learn":[4.416487662],"iteration":300,"passed_time":0.4143792797,"remaining_time":0.9622960681},
{"learn":[4.412369692],"iteration":301,"passed_time":0.4154997314,"remaining_time":0.9603271937},
{"learn":[4.410292209],"iteration":302,"passed_time":0.4184740596,"remaining_time":0.9626284474},
{"learn":[4.405399361],"iteration":303,"passed_time":0.4194725417,"remaining_time":0.9603713455},
{"learn":[4.398995676],"iteration":304,"passed_time":0.4207440483,"remaining_time":0.9587446347},
{"learn":[4.397577171],"iteration":305,"passed_time":0.4220149502,"remaining_time":0.9571188739},
{"learn":[4.395519116],"iteration":306,"passed_time":0.4276956705,"remaining_time":0.9654498359},
{"learn":[4.393981047],"iteration":307,"passed_time":0.4339490755,"remaining_time":0.9749764942},
{"learn":[4.391017864],"iteration":308,"passed_time":0.4371101971,"remaining_time":0.97748591},
{"learn":[4.387279254],"iteration":309,"passed_time":0.4400227179,"remaining_time":0.9794054043},
{"learn":[4.38271854],"iteration":310,"passed_time":0.4416612025,"remaining_time":0.9784712814},
{"learn":[4.377385995],"iteration":311,"passed_time":0.4458571697,"remaining_time":0.9831722205},
{"learn":[4.376173696],"iteration":312,"passed_time":0.4480432406,"remaining_time":0.9834048124},
{"learn":[4.373684936],"iteration":313,"passed_time":0.4497764321,"remaining_time":0.9826325873},
{"learn":[4.371756335],"iteration":314,"passed_time":0.4506377344,"remaining_time":0.9799582478},
{"learn":[4.370129909],"iteration":315,"passed_time":0.4515848611,"remaining_time":0.977481155},
{"learn":[4.365920108],"iteration":316,"passed_time":0.4527269357,"remaining_time":0.9754337446},
{"learn":[4.360463569],"iteration":317,"passed_time":0.4535033581,"remaining_time":0.9726078309},
{"learn":[4.355874372],"iteration":318,"passed_time":0.4543695595,"remaining_time":0.9699864265},
{"learn":[4.350383215],"iteration":319,"passed_time":0.4582310419,"remaining_time":0.973740964},
{"learn":[4.343883493],"iteration":320,"passed_time":0.4603825056,"remaining_time":0.9738309074},
{"learn":[4.342588065],"iteration":321,"passed_time":0.4613658847,"remaining_time":0.9714474218},
{"learn":[4.339177283],"iteration":322,"passed_time":0.4622675156,"remaining_time":0.9689012634},
{"learn":[4.333620075],"iteration":323,"passed_time":0.4631397403,"remaining_time":0.9663039025},
{"learn":[4.329544357],"iteration":324,"passed_time":0.4641491853,"remaining_time":0.964002154},
{"learn":[4.327303051],"iteration":325,"passed_time":0.4655159809,"remaining_time":0.9624471506},
{"learn":[4.325521413],"iteration":326,"passed_time":0.4663551176,"remaining_time":0.9598073216},
{"learn":[4.32342281],"iteration":327,"passed_time":0.4674339677,"remaining_time":0.9576695924},
{"learn":[4.320864529],"iteration":328,"passed_time":0.4685943838,"remaining_time":0.955704655},
{"learn":[4.317818355],"iteration":329,"passed_time":0.4703883992,"remaining_time":0.9550309923},
{"learn":[4.317383424],"iteration":330,"passed_time":0.4712610903,"remaining_time":0.9524884272},
{"learn":[4.312959604],"iteration":331,"passed_time":0.4720640991,"remaining_time":0.9498157174},
{"learn":[4.309460021],"iteration":332,"passed_time":0.4728634963,"remaining_time":0.9471470031},
{"learn":[4.305443208],"iteration":333,"passed_time":0.4737156002,"remaining_time":0.9445945799},
{"learn":[4.304410337],"iteration":334,"passed_time":0.4746976381,"remaining_time":0.9423102368},
{"learn":[4.299255591],"iteration":335,"passed_time":0.4754298045,"remaining_time":0.9395398517},
{"learn":[4.297978591],"iteration":336,"passed_time":0.4924753035,"remaining_time":0.9688757454},
{"learn":[4.292694507],"iteration":337,"passed_time":0.4933651622,"remaining_time":0.966295081},
{"learn":[4.290148241],"iteration":338,"passed_time":0.4948915027,"remaining_time":0.9649654374},
{"learn":[4.289063801],"iteration":339,"passed_time":0.4961900571,"remaining_time":0.9631924638},
{"learn":[4.286440617],"iteration":340,"passed_time":0.497739529,"remaining_time":0.9619071837},
{"learn":[4.283125419],"iteration":341,"passed_time":0.4985924122,"remaining_time":0.9592801382},
{"learn":[4.279385037],"iteration":342,"passed_time":0.4994122351,"remaining_time":0.9566001122},
{"learn":[4.278284207],"iteration":343,"passed_time":0.5001890068,"remaining_time":0.9538488038},
{"learn":[4.275095425],"iteration":344,"passed_time":0.5010916561,"remaining_time":0.9513479268},
{"learn":[4.270331795],"iteration":345,"passed_time":0.5019511661,"remaining_time":0.9487747474},
{"learn":[4.267530933],"iteration":346,"passed_time":0.5026639899,"remaining_time":0.9459354045},
{"learn":[4.26622039],"iteration":347,"passed_time":0.5034367713,"remaining_time":0.9432206174},
{"learn":[4.262131738],"iteration":348,"passed_time":0.5041807864,"remaining_time":0.9404633007},
{"learn":[4.258613092],"iteration":349,"passed_time":0.5049054922,"remaining_time":0.9376816284},
{"learn":[4.255645279],"iteration":350,"passed_time":0.5056647516,"remaining_time":0.9349755664},
{"learn":[4.253076354],"iteration":351,"passed_time":0.5065369598,"remaining_time":0.9324884942},
{"learn":[4.252531727],"iteration":352,"passed_time":0.5077275549,"remaining_time":0.9305941304},
{"learn":[4.247052899],"iteration":353,"passed_time":0.508771606,"remaining_time":0.9284363205},
{"learn":[4.244874829],"iteration":354,"passed_time":0.5099791715,"remaining_time":0.926581875},
{"learn":[4.243825688],"iteration":355,"passed_time":0.5105836553,"remaining_time":0.9236400956},
{"learn":[4.240043114],"iteration":356,"passed_time":0.5117675674,"remaining_time":0.9217550304},
{"learn":[4.235177286],"iteration":357,"passed_time":0.5135042138,"remaining_time":0.9208650985},
{"learn":[4.233883439],"iteration":358,"passed_time":0.5142390848,"remaining_time":0.9181817642},
{"learn":[4.231648599],"iteration":359,"passed_time":0.5149646631,"remaining_time":0.9154927344},
{"learn":[4.230793414],"iteration":360,"passed_time":0.5156993261,"remaining_time":0.9128306631},
{"learn":[4.22887832],"iteration":361,"passed_time":0.5163643348,"remaining_time":0.9100564795},
{"learn":[4.224961576],"iteration":362,"passed_time":0.5170746783,"remaining_time":0.9073734714},
{"learn":[4.222564534],"iteration":363,"passed_time":0.5177843663,"remaining_time":0.9047001564},
{"learn":[4.218992031],"iteration":364,"passed_time":0.5184633887,"remaining_time":0.9019842515},
{"learn":[4.216422786],"iteration":365,"passed_time":0.5195565646,"remaining_time":0.8999968906},
{"learn":[4.213590053],"iteration":366,"passed_time":0.5204341518,"remaining_time":0.8976425561},
{"learn":[4.211896817],"iteration":367,"passed_time":0.52187247,"remaining_time":0.896259242},
{"learn":[4.207429519],"iteration":368,"passed_time":0.5230816498,"remaining_time":0.8944837968},
{"learn":[4.20245575],"iteration":369,"passed_time":0.5238354142,"remaining_time":0.8919359755},
{"learn":[4.198847973],"iteration":370,"passed_time":0.5245176988,"remaining_time":0.8892766376},
{"learn":[4.196464302],"iteration":371,"passed_time":0.525148414,"remaining_time":0.8865408709},
{"learn":[4.19485463],"iteration":372,"passed_time":0.5257741557,"remaining_time":0.8838080311},
{"learn":[4.191578349],"iteration":373,"passed_time":0.526538102,"remaining_time":0.8813177857},
{"learn":[4.188443885],"iteration":374,"passed_time":0.5272851308,"remaining_time":0.8788085514},
{"learn":[4.183084738],"iteration":375,"passed_time":0.5280329367,"remaining_time":0.8763099801},
{"learn":[4.181260081],"iteration":376,"passed_time":0.5286815468,"remaining_time":0.8736567736},
{"learn":[4.179195053],"iteration":377,"passed_time":0.5293777835,"remaining_time":0.8710925433},
{"learn":[4.178245025],"iteration":378,"passed_time":0.5302431099,"remaining_time":0.8688152275},
{"learn":[4.177865476],"iteration":379,"passed_time":0.5315659363,"remaining_time":0.8672917908},
{"learn":[4.173764348],"iteration":380,"passed_time":0.5331304897,"remaining_time":0.8661621342},
{"learn":[4.172267354],"iteration":381,"passed_time":0.5344466886,"remaining_time":0.8646284124},
{"learn":[4.168361438],"iteration":382,"passed_time":0.5353160527,"remaining_time":0.8623759909},
{"learn":[4.167689496],"iteration":383,"passed_time":0.5360243603,"remaining_time":0.8598724114},
{"learn":[4.16348037],"iteration":384,"passed_time":0.5366923662,"remaining_time":0.8573137798},
{"learn":[4.161296959],"iteration":385,"passed_time":0.5374553187,"remaining_time":0.8549159733},
{"learn":[4.15981108],"iteration":386,"passed_time":0.5384213016,"remaining_time":0.8528482116},
{"learn":[4.154869233],"iteration":387,"passed_time":0.540662069,"remaining_time":0.8527968718},
{"learn":[4.150996363],"iteration":388,"passed_time":0.5420313058,"remaining_time":0.8513653671},
{"learn":[4.148100536],"iteration":389,"passed_time":0.5435235618,"remaining_time":0.8501265967},
{"learn":[4.144716161],"iteration":390,"passed_time":0.5448662019,"remaining_time":0.848653496},
{"learn":[4.141802661],"iteration":391,"passed_time":0.5463316407,"remaining_time":0.8473715243},
{"learn":[4.138785322],"iteration":392,"passed_time":0.5470675522,"remaining_time":0.8449618428},
{"learn":[4.135676192],"iteration":393,"passed_time":0.5477587826,"remaining_time":0.8424919347},
{"learn":[4.131935893],"iteration":394,"passed_time":0.5487600023,"remaining_time":0.8405058263},
{"learn":[4.127339057],"iteration":395,"passed_time":0.549475597,"remaining_time":0.8380890419},
{"learn":[4.12062674],"iteration":396,"passed_time":0.5501867268,"remaining_time":0.835674046},
{"learn":[4.11872254],"iteration":397,"passed_time":0.5508635811,"remaining_time":0.8332157685},
{"learn":[4.117255188],"iteration":398,"passed_time":0.5515647546,"remaining_time":0.8308030514},
{"learn":[4.115394999],"iteration":399,"passed_time":0.5522640039,"remaining_time":0.8283960058},
{"learn":[4.110292535],"iteration":400,"passed_time":0.5530071408,"remaining_time":0.8260630358},
{"learn":[4.107386041],"iteration":401,"passed_time":0.5537405254,"remaining_time":0.8237234682},
{"learn":[4.105670768],"iteration":402,"passed_time":0.5547224446,"remaining_time":0.8217600483},
{"learn":[4.101957663],"iteration":403,"passed_time":0.5561633212,"remaining_time":0.8204785629},
{"learn":[4.098363036],"iteration":404,"passed_time":0.5574346895,"remaining_time":0.8189472599},
{"learn":[4.096047088],"iteration":405,"passed_time":0.5587680138,"remaining_time":0.8175078823},
{"learn":[4.094343449],"iteration":406,"passed_time":0.5595378084,"remaining_time":0.8152479616},
{"learn":[4.089231976],"iteration":407,"passed_time":0.56027045,"remaining_time":0.8129414373},
{"learn":[4.08488807],"iteration":408,"passed_time":0.5609034405,"remaining_time":0.8104986144},
{"learn":[4.07985981],"iteration":409,"passed_time":0.5615516503,"remaining_time":0.8080865211},
{"learn":[4.077731355],"iteration":410,"passed_time":0.5622278283,"remaining_time":0.8057230921},
{"learn":[4.073570428],"iteration":411,"passed_time":0.5628728712,"remaining_time":0.8033234181},
{"learn":[4.073489159],"iteration":412,"passed_time":0.5634105516,"remaining_time":0.8007796459},
{"learn":[4.068827098],"iteration":413,"passed_time":0.5640983991,"remaining_time":0.7984581204},
{"learn":[4.066999333],"iteration":414,"passed_time":0.5647154241,"remaining_time":0.7960446339},
{"learn":[4.06426037],"iteration":415,"passed_time":0.5653050248,"remaining_time":0.7936012848},
{"learn":[4.062902974],"iteration":416,"passed_time":0.5660436593,"remaining_time":0.791375188},
{"learn":[4.060471418],"iteration":417,"passed_time":0.56690228,"remaining_time":0.7893232703},
{"learn":[4.057422052],"iteration":418,"passed_time":0.5680952271,"remaining_time":0.7877406371},
{"learn":[4.056376819],"iteration":419,"passed_time":0.5691488753,"remaining_time":0.7859674945},
{"learn":[4.053419085],"iteration":420,"passed_time":0.5704925295,"remaining_time":0.7845966142},
{"learn":[4.050901982],"iteration":421,"passed_time":0.5713574997,"remaining_time":0.7825702247},
{"learn":[4.047042054],"iteration":422,"passed_time":0.5721171612,"remaining_time":0.7804056785},
{"learn":[4.043037544],"iteration":423,"passed_time":0.5727770084,"remaining_time":0.7781121623},
{"learn":[4.039281364],"iteration":424,"passed_time":0.5733953715,"remaining_time":0.7757702085},
{"learn":[4.035659366],"iteration":425,"passed_time":0.5740489638,"remaining_time":0.7734838151},
{"learn":[4.034826248],"iteration":426,"passed_time":0.5746569362,"remaining_time":0.7711438512},
{"learn":[4.031162181],"iteration":427,"passed_time":0.5753508536,"remaining_time":0.7689268418},
{"learn":[4.026800639],"iteration":428,"passed_time":0.5759491147,"remaining_time":0.7665896143},
{"learn":[4.025538166],"iteration":429,"passed_time":0.5765677847,"remaining_time":0.7642875285},
{"learn":[4.022631849],"iteration":430,"passed_time":0.5772122964,"remaining_time":0.7620273704},
{"learn":[4.019400332],"iteration":431,"passed_time":0.577890063,"remaining_time":0.7598184162},
{"learn":[4.014856115],"iteration":432,"passed_time":0.5789661974,"remaining_time":0.7581381845},
{"learn":[4.011031495],"iteration":433,"passed_time":0.5803663144,"remaining_time":0.756883258},
{"learn":[4.007458749],"iteration":434,"passed_time":0.581730343,"remaining_time":0.7555807903},
{"learn":[4.004075986],"iteration":435,"passed_time":0.5830377068,"remaining_time":0.75420474},
{"learn":[4.00052387],"iteration":436,"passed_time":0.5838355621,"remaining_time":0.7521725892},
{"learn":[3.999371427],"iteration":437,"passed_time":0.5845739505,"remaining_time":0.7500697721},
{"learn":[3.995988572],"iteration":438,"passed_time":0.5852177472,"remaining_time":0.7478522919},
{"learn":[3.994233456],"iteration":439,"passed_time":0.5858343444,"remaining_time":0.7456073474},
{"learn":[3.991181377],"iteration":440,"passed_time":0.5864971762,"remaining_time":0.7434283934},
{"learn":[3.988497883],"iteration":441,"passed_time":0.5871299483,"remaining_time":0.741218351},
{"learn":[3.984743122],"iteration":442,"passed_time":0.5877526311,"remaining_time":0.7390027439},
{"learn":[3.98301137],"iteration":443,"passed_time":0.588373741,"remaining_time":0.7367923424},
{"learn":[3.979974821],"iteration":444,"passed_time":0.5889811704,"remaining_time":0.7345720215},
{"learn":[3.975592306],"iteration":445,"passed_time":0.5896720576,"remaining_time":0.7324626007},
{"learn":[3.972815633],"iteration":446,"passed_time":0.5904378067,"remaining_time":0.7304521411},
{"learn":[3.971829884],"iteration":447,"passed_time":0.591592887,"remaining_time":0.72892695},
{"learn":[3.969936373],"iteration":448,"passed_time":0.5927133846,"remaining_time":0.7273609687},
{"learn":[3.96540322],"iteration":449,"passed_time":0.5941795901,"remaining_time":0.7262194991},
{"learn":[3.959801182],"iteration":450,"passed_time":0.5952114703,"remaining_time":0.7245478874},
{"learn":[3.956945028],"iteration":451,"passed_time":0.5959064042,"remaining_time":0.7224705962},
{"learn":[3.955966769],"iteration":452,"passed_time":0.5964900081,"remaining_time":0.7202649767},
{"learn":[3.950174676],"iteration":453,"passed_time":0.5971549176,"remaining_time":0.7181642841},
{"learn":[3.948788341],"iteration":454,"passed_time":0.5978272933,"remaining_time":0.7160788458},
{"learn":[3.944494525],"iteration":455,"passed_time":0.5984431349,"remaining_time":0.7139321609},
{"learn":[3.942399577],"iteration":456,"passed_time":0.5990722155,"remaining_time":0.7118079059},
{"learn":[3.93905738],"iteration":457,"passed_time":0.5996799263,"remaining_time":0.7096648909},
{"learn":[3.935593971],"iteration":458,"passed_time":0.6003385743,"remaining_time":0.7075886029},
{"learn":[3.933570053],"iteration":459,"passed_time":0.6009639534,"remaining_time":0.7054794235},
{"learn":[3.930807557],"iteration":460,"passed_time":0.6015604026,"remaining_time":0.7033428568},
{"learn":[3.929322585],"iteration":461,"passed_time":0.6022482148,"remaining_time":0.7013193498},
{"learn":[3.928103857],"iteration":462,"passed_time":0.6032048928,"remaining_time":0.6996134501},
{"learn":[3.92653266],"iteration":463,"passed_time":0.6043981887,"remaining_time":0.6981841145},
{"learn":[3.923612124],"iteration":464,"passed_time":0.605447081,"remaining_time":0.6965896524},
{"learn":[3.91941325],"iteration":465,"passed_time":0.6066716683,"remaining_time":0.6951988645},
{"learn":[3.918008795],"iteration":466,"passed_time":0.6074534322,"remaining_time":0.6933033819},
{"learn":[3.914454858],"iteration":467,"passed_time":0.6081605694,"remaining_time":0.6913278268},
{"learn":[3.910593205],"iteration":468,"passed_time":0.6088199513,"remaining_time":0.6893036122},
{"learn":[3.906818756],"iteration":469,"passed_time":0.6094773022,"remaining_time":0.6872829152},
{"learn":[3.90516587],"iteration":470,"passed_time":0.6100975756,"remaining_time":0.6852263641},
{"learn":[3.904688036],"iteration":471,"passed_time":0.6107346215,"remaining_time":0.6831946613},
{"learn":[3.903774203],"iteration":472,"passed_time":0.6113714276,"remaining_time":0.6811685885},
{"learn":[3.901683842],"iteration":473,"passed_time":0.6119927129,"remaining_time":0.679131154},
{"learn":[3.899023706],"iteration":474,"passed_time":0.6126031364,"remaining_time":0.6770876771},
{"learn":[3.897518039],"iteration":475,"passed_time":0.6132348305,"remaining_time":0.6750736369},
{"learn":[3.893496691],"iteration":476,"passed_time":0.6138395655,"remaining_time":0.6730358339},
{"learn":[3.891923296],"iteration":477,"passed_time":0.6146819079,"remaining_time":0.6712635061},
{"learn":[3.888541435],"iteration":478,"passed_time":0.6159510423,"remaining_time":0.6699592756},
{"learn":[3.884444672],"iteration":479,"passed_time":0.6170969306,"remaining_time":0.6685216748},
{"learn":[3.883066914],"iteration":480,"passed_time":0.619548956,"remaining_time":0.6684946116},
{"learn":[3.882024764],"iteration":481,"passed_time":0.6206123814,"remaining_time":0.6669651734},
{"learn":[3.880111854],"iteration":482,"passed_time":0.6216731551,"remaining_time":0.6654348264},
{"learn":[3.876087803],"iteration":483,"passed_time":0.6227120799,"remaining_time":0.6638831265},
{"learn":[3.874575434],"iteration":484,"passed_time":0.6235963991,"remaining_time":0.6621693723},
{"learn":[3.873996337],"iteration":485,"passed_time":0.6245799985,"remaining_time":0.6605640313},
{"learn":[3.87099151],"iteration":486,"passed_time":0.625519523,"remaining_time":0.6589148158},
{"learn":[3.869141363],"iteration":487,"passed_time":0.6264331439,"remaining_time":0.6572413313},
{"learn":[3.864885719],"iteration":488,"passed_time":0.6275013337,"remaining_time":0.6557324775},
{"learn":[3.863069536],"iteration":489,"passed_time":0.6290844572,"remaining_time":0.6547613738},
{"learn":[3.858565133],"iteration":490,"passed_time":0.631310664,"remaining_time":0.6544544358},
{"learn":[3.856203657],"iteration":491,"passed_time":0.6328970406,"remaining_time":0.6534790582},
{"learn":[3.853578144],"iteration":492,"passed_time":0.6339061386,"remaining_time":0.65190753},
{"learn":[3.851639616],"iteration":493,"passed_time":0.6348430101,"remaining_time":0.6502642978},
{"learn":[3.84874742],"iteration":494,"passed_time":0.6357272505,"remaining_time":0.6485702253},
{"learn":[3.847131517],"iteration":495,"passed_time":0.6366549978,"remaining_time":0.6469236268},
{"learn":[3.844589686],"iteration":496,"passed_time":0.637771154,"remaining_time":0.6454706045},
{"learn":[3.843231122],"iteration":497,"passed_time":0.6388422762,"remaining_time":0.6439735395},
{"learn":[3.840774799],"iteration":498,"passed_time":0.6401033549,"remaining_time":0.6426688994},
{"learn":[3.838446601],"iteration":499,"passed_time":0.6423776369,"remaining_time":0.6423776369},
{"learn":[3.835763815],"iteration":500,"passed_time":0.6441181483,"remaining_time":0.6415468184},
{"learn":[3.832719423],"iteration":501,"passed_time":0.6448565799,"remaining_time":0.6397182805},
{"learn":[3.830829503],"iteration":502,"passed_time":0.6455281123,"remaining_time":0.6378279758},
{"learn":[3.828311724],"iteration":503,"passed_time":0.6462551858,"remaining_time":0.6359971669},
{"learn":[3.825205782],"iteration":504,"passed_time":0.6470028856,"remaining_time":0.6341909472},
{"learn":[3.822718693],"iteration":505,"passed_time":0.64771564,"remaining_time":0.6323547948},
{"learn":[3.819774953],"iteration":506,"passed_time":0.648368518,"remaining_time":0.6304648509},
{"learn":[3.818353639],"iteration":507,"passed_time":0.6490943073,"remaining_time":0.6286503922},
{"learn":[3.814776604],"iteration":508,"passed_time":0.649803037,"remaining_time":0.6268237548},
{"learn":[3.814051754],"iteration":509,"passed_time":0.6505397571,"remaining_time":0.625028394},
{"learn":[3.811854467],"iteration":510,"passed_time":0.6515718092,"remaining_time":0.623519794},
{"learn":[3.807550071],"iteration":511,"passed_time":0.6530515023,"remaining_time":0.6224397131},
{"learn":[3.80669406],"iteration":512,"passed_time":0.654511592,"remaining_time":0.6213394645},
{"learn":[3.803275804],"iteration":513,"passed_time":0.6553030492,"remaining_time":0.6196056068},
{"learn":[3.802833916],"iteration":514,"passed_time":0.6560075503,"remaining_time":0.6177935183},
{"learn":[3.798749188],"iteration":515,"passed_time":0.6567008358,"remaining_time":0.6159752026},
{"learn":[3.797225193],"iteration":516,"passed_time":0.65744751,"remaining_time":0.6142111167},
{"learn":[3.794818627],"iteration":517,"passed_time":0.6581129614,"remaining_time":0.612375381},
{"learn":[3.792057626],"iteration":518,"passed_time":0.6588611594,"remaining_time":0.6106208433},
{"learn":[3.788380223],"iteration":519,"passed_time":0.659604597,"remaining_time":0.6088657818},
{"learn":[3.785553905],"iteration":520,"passed_time":0.6603422986,"remaining_time":0.6071093302},
{"learn":[3.784229933],"iteration":521,"passed_time":0.6610315413,"remaining_time":0.6053124076},
{"learn":[3.782861662],"iteration":522,"passed_time":0.6616890106,"remaining_time":0.6034907419},
{"learn":[3.78085347],"iteration":523,"passed_time":0.6625041549,"remaining_time":0.6018167514},
{"learn":[3.779983865],"iteration":524,"passed_time":0.6636997779,"remaining_time":0.6004902752},
{"learn":[3.777022015],"iteration":525,"passed_time":0.6648809601,"remaining_time":0.5991512834},
{"learn":[3.775429476],"iteration":526,"passed_time":0.6662282411,"remaining_time":0.5979619697},
{"learn":[3.771778322],"iteration":527,"passed_time":0.6671122283,"remaining_time":0.5963579011},
{"learn":[3.768647695],"iteration":528,"passed_time":0.6677954724,"remaining_time":0.5945778213},
{"learn":[3.768432884],"iteration":529,"passed_time":0.668509462,"remaining_time":0.5928291455},
{"learn":[3.764354318],"iteration":530,"passed_time":0.6692224803,"remaining_time":0.591083509},
{"learn":[3.761653817],"iteration":531,"passed_time":0.6699197189,"remaining_time":0.589327873},
{"learn":[3.758092461],"iteration":532,"passed_time":0.6706181732,"remaining_time":0.5875772737},
{"learn":[3.755323027],"iteration":533,"passed_time":0.6712856823,"remaining_time":0.5858036104},
{"learn":[3.75455294],"iteration":534,"passed_time":0.6720253651,"remaining_time":0.5840968127},
{"learn":[3.752935423],"iteration":535,"passed_time":0.6726788413,"remaining_time":0.582318997},
{"learn":[3.75169392],"iteration":536,"passed_time":0.6733438879,"remaining_time":0.5805553447},
{"learn":[3.749534619],"iteration":537,"passed_time":0.6741294112,"remaining_time":0.5788992341},
{"learn":[3.747009466],"iteration":538,"passed_time":0.6753038869,"remaining_time":0.5775790202},
{"learn":[3.74592398],"iteration":539,"passed_time":0.6765346471,"remaining_time":0.576307292},
{"learn":[3.743492817],"iteration":540,"passed_time":0.6786408107,"remaining_time":0.5757784327},
{"learn":[3.741768583],"iteration":541,"passed_time":0.6793665698,"remaining_time":0.5740772859},
{"learn":[3.739633162],"iteration":542,"passed_time":0.6800858158,"remaining_time":0.5723742501},
{"learn":[3.739454356],"iteration":543,"passed_time":0.680814991,"remaining_time":0.5706831543},
{"learn":[3.736458962],"iteration":544,"passed_time":0.6815677907,"remaining_time":0.5690153115},
{"learn":[3.735440993],"iteration":545,"passed_time":0.6822452555,"remaining_time":0.5672881795},
{"learn":[3.732333193],"iteration":546,"passed_time":0.6829921353,"remaining_time":0.5656223716},
{"learn":[3.730270395],"iteration":547,"passed_time":0.6836925634,"remaining_time":0.5639216034},
{"learn":[3.726091803],"iteration":548,"passed_time":0.6844581352,"remaining_time":0.5622779945},
{"learn":[3.72513364],"iteration":549,"passed_time":0.6851415351,"remaining_time":0.5605703469},
{"learn":[3.722704856],"iteration":550,"passed_time":0.6858351978,"remaining_time":0.55887478},
{"learn":[3.721174111],"iteration":551,"passed_time":0.686985109,"remaining_time":0.5575531319},
{"learn":[3.719138821],"iteration":552,"passed_time":0.688478149,"remaining_time":0.5565094622},
{"learn":[3.716910488],"iteration":553,"passed_time":0.6900553317,"remaining_time":0.5555319096},
{"learn":[3.715588747],"iteration":554,"passed_time":0.6908236762,"remaining_time":0.5539036683},
{"learn":[3.714619202],"iteration":555,"passed_time":0.6915746816,"remaining_time":0.5522646738},
{"learn":[3.713245078],"iteration":556,"passed_time":0.6923368371,"remaining_time":0.5506377358},
{"learn":[3.709809688],"iteration":557,"passed_time":0.693054902,"remaining_time":0.5489789726},
{"learn":[3.706532175],"iteration":558,"passed_time":0.6938126613,"remaining_time":0.5473548902},
{"learn":[3.703941256],"iteration":559,"passed_time":0.6945737502,"remaining_time":0.545736518},
{"learn":[3.702797899],"iteration":560,"passed_time":0.6952909901,"remaining_time":0.5440868889},
{"learn":[3.699764861],"iteration":561,"passed_time":0.6962934139,"remaining_time":0.5426628386},
{"learn":[3.696692467],"iteration":562,"passed_time":0.6974437977,"remaining_time":0.5413551325},
{"learn":[3.695670623],"iteration":563,"passed_time":0.6986149752,"remaining_time":0.5400640588},
{"learn":[3.693372365],"iteration":564,"passed_time":0.7001026986,"remaining_time":0.539017122},
{"learn":[3.692221091],"iteration":565,"passed_time":0.7007958152,"remaining_time":0.5373593354},
{"learn":[3.690572929],"iteration":566,"passed_time":0.7014581196,"remaining_time":0.5356814212},
{"learn":[3.686518788],"iteration":567,"passed_time":0.7022156181,"remaining_time":0.5340794842},
{"learn":[3.683546238],"iteration":568,"passed_time":0.7029413204,"remaining_time":0.5324564308},
{"learn":[3.679461558],"iteration":569,"passed_time":0.7036617173,"remaining_time":0.5308325236},
{"learn":[3.676267539],"iteration":570,"passed_time":0.7043399079,"remaining_time":0.5291800709},
{"learn":[3.674981557],"iteration":571,"passed_time":0.7050539967,"remaining_time":0.5275578856},
{"learn":[3.671595251],"iteration":572,"passed_time":0.7057533275,"remaining_time":0.5259278724},
{"learn":[3.669813041],"iteration":573,"passed_time":0.7065316925,"remaining_time":0.5243597578},
{"learn":[3.668618857],"iteration":574,"passed_time":0.7072813941,"remaining_time":0.5227732044},
{"learn":[3.666348695],"iteration":575,"passed_time":0.7080718062,"remaining_time":0.521219524},
{"learn":[3.662593315],"iteration":576,"passed_time":0.7091255245,"remaining_time":0.5198615197},
{"learn":[3.660454464],"iteration":577,"passed_time":0.7106534122,"remaining_time":0.5188507612},
{"learn":[3.658451712],"iteration":578,"passed_time":0.7125253457,"remaining_time":0.5180883774},
{"learn":[3.656107044],"iteration":579,"passed_time":0.7133513607,"remaining_time":0.5165647784},
{"learn":[3.653771696],"iteration":580,"passed_time":0.7140829679,"remaining_time":0.5149754966},
{"learn":[3.652714028],"iteration":581,"passed_time":0.7147361626,"remaining_time":0.5133328453},
{"learn":[3.649942033],"iteration":582,"passed_time":0.7154178663,"remaining_time":0.5117139798},
{"learn":[3.649237276],"iteration":583,"passed_time":0.7161255068,"remaining_time":0.5101167993},
{"learn":[3.646388923],"iteration":584,"passed_time":0.7168349151,"remaining_time":0.5085239141},
{"learn":[3.645549006],"iteration":585,"passed_time":0.717582618,"remaining_time":0.5069610987},
{"learn":[3.644332812],"iteration":586,"passed_time":0.718330826,"remaining_time":0.5054014159},
{"learn":[3.641850949],"iteration":587,"passed_time":0.7191076038,"remaining_time":0.5038645115},
{"learn":[3.639453648],"iteration":588,"passed_time":0.7199160973,"remaining_time":0.5023523192},
{"learn":[3.63640346],"iteration":589,"passed_time":0.7212268099,"remaining_time":0.501191512},
{"learn":[3.634331537],"iteration":590,"passed_time":0.7227173644,"remaining_time":0.5001546566},
{"learn":[3.631253588],"iteration":591,"passed_time":0.7245002875,"remaining_time":0.4993177657},
{"learn":[3.627688241],"iteration":592,"passed_time":0.7252285566,"remaining_time":0.4977538323},
{"learn":[3.626480592],"iteration":593,"passed_time":0.725962955,"remaining_time":0.4961969019},
{"learn":[3.623137909],"iteration":594,"passed_time":0.7266254796,"remaining_time":0.4945938138},
{"learn":[3.62068814],"iteration":595,"passed_time":0.7273704483,"remaining_time":0.493049767},
{"learn":[3.616890191],"iteration":596,"passed_time":0.7281446529,"remaining_time":0.4915281325},
{"learn":[3.615482683],"iteration":597,"passed_time":0.7288887312,"remaining_time":0.4899887457},
{"learn":[3.613811566],"iteration":598,"passed_time":0.7297821226,"remaining_time":0.4885519719},
{"learn":[3.613251281],"iteration":599,"passed_time":0.7307772682,"remaining_time":0.4871848454},
{"learn":[3.6120668],"iteration":600,"passed_time":0.7317595202,"remaining_time":0.4858103969},
{"learn":[3.61050671],"iteration":601,"passed_time":0.7327071068,"remaining_time":0.4844143331},
{"learn":[3.609172431],"iteration":602,"passed_time":0.7343832468,"remaining_time":0.4834994179},
{"learn":[3.608080945],"iteration":603,"passed_time":0.7362279884,"remaining_time":0.4826925222},
{"learn":[3.60533989],"iteration":604,"passed_time":0.7370498863,"remaining_time":0.4812143886},
{"learn":[3.604775352],"iteration":605,"passed_time":0.7377177386,"remaining_time":0.4796382657},
{"learn":[3.603216265],"iteration":606,"passed_time":0.7384235802,"remaining_time":0.4780897315},
{"learn":[3.601691646],"iteration":607,"passed_time":0.7391881052,"remaining_time":0.4765818047},
{"learn":[3.599367758],"iteration":608,"passed_time":0.7399464704,"remaining_time":0.4750723644},
{"learn":[3.595758546],"iteration":609,"passed_time":0.7406677286,"remaining_time":0.4735416626},
{"learn":[3.592374968],"iteration":610,"passed_time":0.7414340751,"remaining_time":0.4720423162},
{"learn":[3.588571682],"iteration":611,"passed_time":0.7421891788,"remaining_time":0.4705382375},
{"learn":[3.585683233],"iteration":612,"passed_time":0.742902428,"remaining_time":0.4690101789},
{"learn":[3.582718899],"iteration":613,"passed_time":0.7436713428,"remaining_time":0.4675197693},
{"learn":[3.579701667],"iteration":614,"passed_time":0.7444717714,"remaining_time":0.4660514342},
{"learn":[3.577063866],"iteration":615,"passed_time":0.745498031,"remaining_time":0.4647260453},
{"learn":[3.575250689],"iteration":616,"passed_time":0.7468634306,"remaining_time":0.4636121457},
{"learn":[3.574138537],"iteration":617,"passed_time":0.748793522,"remaining_time":0.4628464813},
{"learn":[3.571111262],"iteration":618,"passed_time":0.7495558863,"remaining_time":0.461358308},
{"learn":[3.570036043],"iteration":619,"passed_time":0.7504415303,"remaining_time":0.4599480347},
{"learn":[3.568784584],"iteration":620,"passed_time":0.7511906226,"remaining_time":0.4584561127},
{"learn":[3.56676922],"iteration":621,"passed_time":0.7519512707,"remaining_time":0.4569736018},
{"learn":[3.565468584],"iteration":622,"passed_time":0.7528200014,"remaining_time":0.4555588131},
{"learn":[3.563955592],"iteration":623,"passed_time":0.7536306584,"remaining_time":0.4541107813},
{"learn":[3.561878138],"iteration":624,"passed_time":0.7544169174,"remaining_time":0.4526501504},
{"learn":[3.561169686],"iteration":625,"passed_time":0.7551284248,"remaining_time":0.4511470142},
{"learn":[3.55849113],"iteration":626,"passed_time":0.7559508915,"remaining_time":0.4497124123},
{"learn":[3.55576918],"iteration":627,"passed_time":0.7568591338,"remaining_time":0.4483305697},
{"learn":[3.553920352],"iteration":628,"passed_time":0.7584776921,"remaining_time":0.4473691952},
{"learn":[3.550878506],"iteration":629,"passed_time":0.7596759933,"remaining_time":0.4461589167},
{"learn":[3.548634273],"iteration":630,"passed_time":0.7611125532,"remaining_time":0.4450880066},
{"learn":[3.546536456],"iteration":631,"passed_time":0.7617930708,"remaining_time":0.4435757121},
{"learn":[3.544167691],"iteration":632,"passed_time":0.7625129748,"remaining_time":0.4420888811},
{"learn":[3.542010445],"iteration":633,"passed_time":0.763315524,"remaining_time":0.4406521795},
{"learn":[3.53863115],"iteration":634,"passed_time":0.7642492681,"remaining_time":0.4392928864},
{"learn":[3.536159873],"iteration":635,"passed_time":0.7650809864,"remaining_time":0.4378765394},
{"learn":[3.534741147],"iteration":636,"passed_time":0.7658952316,"remaining_time":0.4364520707},
{"learn":[3.532569004],"iteration":637,"passed_time":0.7665827152,"remaining_time":0.4349575908},
{"learn":[3.531550908],"iteration":638,"passed_time":0.7673141915,"remaining_time":0.43349049},
{"learn":[3.527999437],"iteration":639,"passed_time":0.7682472201,"remaining_time":0.4321390613},
{"learn":[3.526895936],"iteration":640,"passed_time":0.7692458608,"remaining_time":0.4308256849},
{"learn":[3.525134811],"iteration":641,"passed_time":0.7704612583,"remaining_time":0.4296341596},
{"learn":[3.52419523],"iteration":642,"passed_time":0.7724518355,"remaining_time":0.4288729476},
{"learn":[3.521120107],"iteration":643,"passed_time":0.7732229582,"remaining_time":0.4274338092},
{"learn":[3.51864355],"iteration":644,"passed_time":0.7740208864,"remaining_time":0.4260114956},
{"learn":[3.51705645],"iteration":645,"passed_time":0.7748516017,"remaining_time":0.424609082},
{"learn":[3.514364472],"iteration":646,"passed_time":0.7755616806,"remaining_time":0.4231426171},
{"learn":[3.512168718],"iteration":647,"passed_time":0.7762952265,"remaining_time":0.4216912342},
{"learn":[3.509960473],"iteration":648,"passed_time":0.7770343054,"remaining_time":0.4202450557},
{"learn":[3.509435655],"iteration":649,"passed_time":0.7776956546,"remaining_time":0.4187591986},
{"learn":[3.507158437],"iteration":650,"passed_time":0.7783248175,"remaining_time":0.4172586195},
{"learn":[3.505596736],"iteration":651,"passed_time":0.779038341,"remaining_time":0.4158057403},
{"learn":[3.502259655],"iteration":652,"passed_time":0.7798252484,"remaining_time":0.4143941213},
{"learn":[3.500740366],"iteration":653,"passed_time":0.7807737748,"remaining_time":0.4130699176},
{"learn":[3.499240586],"iteration":654,"passed_time":0.7819837899,"remaining_time":0.4118845916},
{"learn":[3.496290191],"iteration":655,"passed_time":0.7844853827,"remaining_time":0.4113764811},
{"learn":[3.494096071],"iteration":656,"passed_time":0.7852752394,"remaining_time":0.4099686562},
{"learn":[3.4912574],"iteration":657,"passed_time":0.785957727,"remaining_time":0.4085069037},
{"learn":[3.488639276],"iteration":658,"passed_time":0.7866698526,"remaining_time":0.4070628524},
{"learn":[3.486613009],"iteration":659,"passed_time":0.7874383262,"remaining_time":0.4056500468},
{"learn":[3.483791598],"iteration":660,"passed_time":0.7881891255,"remaining_time":0.4042301264},
{"learn":[3.480552407],"iteration":661,"passed_time":0.7889119712,"remaining_time":0.4027979551},
{"learn":[3.477582365],"iteration":662,"passed_time":0.7897092739,"remaining_time":0.4014057697},
{"learn":[3.477194764],"iteration":663,"passed_time":0.7903791947,"remaining_time":0.3999509178},
{"learn":[3.473844111],"iteration":664,"passed_time":0.7911913204,"remaining_time":0.3985700637},
{"learn":[3.470586723],"iteration":665,"passed_time":0.791901903,"remaining_time":0.3971399934},
{"learn":[3.465890756],"iteration":666,"passed_time":0.7927783182,"remaining_time":0.3957948725},
{"learn":[3.462224996],"iteration":667,"passed_time":0.7938927494,"remaining_time":0.3945694503},
{"learn":[3.461355243],"iteration":668,"passed_time":0.7957360127,"remaining_time":0.3937049629},
{"learn":[3.460756592],"iteration":669,"passed_time":0.7966020521,"remaining_time":0.3923562346},
{"learn":[3.459327918],"iteration":670,"passed_time":0.7972765412,"remaining_time":0.3909150254},
{"learn":[3.458745877],"iteration":671,"passed_time":0.7979556183,"remaining_time":0.3894783375},
{"learn":[3.458149222],"iteration":672,"passed_time":0.7986982942,"remaining_time":0.3880748027},
{"learn":[3.457501669],"iteration":673,"passed_time":0.799363698,"remaining_time":0.386635854},
{"learn":[3.454471304],"iteration":674,"passed_time":0.8000692513,"remaining_time":0.3852185284},
{"learn":[3.45096748],"iteration":675,"passed_time":0.8007982488,"remaining_time":0.3838145453},
{"learn":[3.450344213],"iteration":676,"passed_time":0.8015407404,"remaining_time":0.3824189943},
{"learn":[3.449979595],"iteration":677,"passed_time":0.8022096195,"remaining_time":0.3809904093},
{"learn":[3.448657169],"iteration":678,"passed_time":0.8028780857,"remaining_time":0.3795638667},
{"learn":[3.446789177],"iteration":679,"passed_time":0.8036294365,"remaining_time":0.3781785584},
{"learn":[3.443252244],"iteration":680,"passed_time":0.8046532289,"remaining_time":0.3769227313},
{"learn":[3.439957213],"iteration":681,"passed_time":0.8059422876,"remaining_time":0.3757912719},
{"learn":[3.437812339],"iteration":682,"passed_time":0.808641457,"remaining_time":0.3753138241},
{"learn":[3.435329771],"iteration":683,"passed_time":0.8094595676,"remaining_time":0.3739608529},
{"learn":[3.433616057],"iteration":684,"passed_time":0.8101438552,"remaining_time":0.3725479042},
{"learn":[3.4325958],"iteration":685,"passed_time":0.8108406167,"remaining_time":0.3711427896},
{"learn":[3.431297917],"iteration":686,"passed_time":0.8114980128,"remaining_time":0.369721802},
{"learn":[3.430152922],"iteration":687,"passed_time":0.8121845068,"remaining_time":0.3683162298},
{"learn":[3.428766591],"iteration":688,"passed_time":0.8129593272,"remaining_time":0.3669526136},
{"learn":[3.42645156],"iteration":689,"passed_time":0.8136459901,"remaining_time":0.365551097},
{"learn":[3.424550717],"iteration":690,"passed_time":0.8143236847,"remaining_time":0.364147639},
{"learn":[3.422739182],"iteration":691,"passed_time":0.8150067495,"remaining_time":0.3627486689},
{"learn":[3.421824603],"iteration":692,"passed_time":0.8157342565,"remaining_time":0.3613714527},
{"learn":[3.420869631],"iteration":693,"passed_time":0.8165530534,"remaining_time":0.3600363607},
{"learn":[3.417535592],"iteration":694,"passed_time":0.8180805378,"remaining_time":0.3590137612},
{"learn":[3.416632535],"iteration":695,"passed_time":0.8219247905,"remaining_time":0.3590016326},
{"learn":[3.416180586],"iteration":696,"passed_time":0.8227330462,"remaining_time":0.3576586987},
{"learn":[3.414970841],"iteration":697,"passed_time":0.8235582887,"remaining_time":0.3563246464},
{"learn":[3.41339189],"iteration":698,"passed_time":0.8244253185,"remaining_time":0.3550100442},
{"learn":[3.411352966],"iteration":699,"passed_time":0.8251559315,"remaining_time":0.3536382564},
{"learn":[3.410478715],"iteration":700,"passed_time":0.825887338,"remaining_time":0.3522686363},
{"learn":[3.409641476],"iteration":701,"passed_time":0.8266024969,"remaining_time":0.3508939374},
{"learn":[3.40672297],"iteration":702,"passed_time":0.827390161,"remaining_time":0.3495517465},
{"learn":[3.404567269],"iteration":703,"passed_time":0.8281106445,"remaining_time":0.3481828846},
{"learn":[3.402846006],"iteration":704,"passed_time":0.8288392146,"remaining_time":0.3468192458},
{"learn":[3.401588953],"iteration":705,"passed_time":0.8298179221,"remaining_time":0.345561571},
{"learn":[3.399813139],"iteration":706,"passed_time":0.8311030426,"remaining_time":0.3444316711},
{"learn":[3.399198762],"iteration":707,"passed_time":0.8331497668,"remaining_time":0.3436154405},
{"learn":[3.396990992],"iteration":708,"passed_time":0.8401577339,"remaining_time":0.3448320177},
{"learn":[3.396393724],"iteration":709,"passed_time":0.8415569958,"remaining_time":0.3437345476},
{"learn":[3.394496151],"iteration":710,"passed_time":0.8432156035,"remaining_time":0.3427416447},
{"learn":[3.392548721],"iteration":711,"passed_time":0.8445450237,"remaining_time":0.3416137174},
{"learn":[3.389168687],"iteration":712,"passed_time":0.8453060203,"remaining_time":0.3402564205},
{"learn":[3.388249871],"iteration":713,"passed_time":0.8460435741,"remaining_time":0.3388914036},
{"learn":[3.384887591],"iteration":714,"passed_time":0.8468461562,"remaining_time":0.3375540623},
{"learn":[3.382216061],"iteration":715,"passed_time":0.8479845293,"remaining_time":0.3363514055},
{"learn":[3.380999546],"iteration":716,"passed_time":0.8489060133,"remaining_time":0.3350633218},
{"learn":[3.379101453],"iteration":717,"passed_time":0.8501065767,"remaining_time":0.33388587},
{"learn":[3.377191047],"iteration":718,"passed_time":0.8519729328,"remaining_time":0.3329685593},
{"learn":[3.373796794],"iteration":719,"passed_time":0.8543537186,"remaining_time":0.3322486684},
{"learn":[3.372800333],"iteration":720,"passed_time":0.8556555958,"remaining_time":0.331106673},
{"learn":[3.370683933],"iteration":721,"passed_time":0.8565121576,"remaining_time":0.3297927698},
{"learn":[3.367675935],"iteration":722,"passed_time":0.8572794826,"remaining_time":0.3284459429},
{"learn":[3.366459222],"iteration":723,"passed_time":0.8580143797,"remaining_time":0.3270883547},
{"learn":[3.365447587],"iteration":724,"passed_time":0.8587664355,"remaining_time":0.3257389928},
{"learn":[3.364134405],"iteration":725,"passed_time":0.859474724,"remaining_time":0.3243747581},
{"learn":[3.362328175],"iteration":726,"passed_time":0.8602569724,"remaining_time":0.323040101},
{"learn":[3.359472915],"iteration":727,"passed_time":0.8610483185,"remaining_time":0.3217103608},
{"learn":[3.357427878],"iteration":728,"passed_time":0.8618522181,"remaining_time":0.3203867642},
{"learn":[3.355203387],"iteration":729,"passed_time":0.8628374364,"remaining_time":0.3191316545},
{"learn":[3.353515752],"iteration":730,"passed_time":0.8642555139,"remaining_time":0.3180365708},
{"learn":[3.352571911],"iteration":731,"passed_time":0.8660663863,"remaining_time":0.3170844147},
{"learn":[3.349308203],"iteration":732,"passed_time":0.8668886718,"remaining_time":0.3157698163},
{"learn":[3.34877652],"iteration":733,"passed_time":0.8676895949,"remaining_time":0.3144488178},
{"learn":[3.348260008],"iteration":734,"passed_time":0.8684782452,"remaining_time":0.3131248095},
{"learn":[3.345026102],"iteration":735,"passed_time":0.8692636589,"remaining_time":0.311801095},
{"learn":[3.343739418],"iteration":736,"passed_time":0.8700553915,"remaining_time":0.3104810963},
{"learn":[3.341592203],"iteration":737,"passed_time":0.8707623173,"remaining_time":0.3091324216},
{"learn":[3.339979101],"iteration":738,"passed_time":0.8715961716,"remaining_time":0.3078303123},
{"learn":[3.339210364],"iteration":739,"passed_time":0.87244108,"remaining_time":0.3065333524},
{"learn":[3.338428699],"iteration":740,"passed_time":0.8732150233,"remaining_time":0.3052128084},
{"learn":[3.336187469],"iteration":741,"passed_time":0.8741165328,"remaining_time":0.3039380936},
{"learn":[3.335372956],"iteration":742,"passed_time":0.8755472449,"remaining_time":0.302847432},
{"learn":[3.33452325],"iteration":743,"passed_time":0.8769306915,"remaining_time":0.3017395928},
{"learn":[3.332333219],"iteration":744,"passed_time":0.8787364274,"remaining_time":0.3007755557},
{"learn":[3.331772834],"iteration":745,"passed_time":0.8795359085,"remaining_time":0.2994666498},
{"learn":[3.329677052],"iteration":746,"passed_time":0.8803139487,"remaining_time":0.2981518461},
{"learn":[3.3285384],"iteration":747,"passed_time":0.8809787011,"remaining_time":0.2968003111},
{"learn":[3.326019471],"iteration":748,"passed_time":0.8816630527,"remaining_time":0.2954571779},
{"learn":[3.321949728],"iteration":749,"passed_time":0.8823385566,"remaining_time":0.2941128522},
{"learn":[3.31902531],"iteration":750,"passed_time":0.8830533214,"remaining_time":0.2927833249},
{"learn":[3.317277211],"iteration":751,"passed_time":0.883876937,"remaining_time":0.2914913303},
{"learn":[3.316902894],"iteration":752,"passed_time":0.8846317277,"remaining_time":0.2901780036},
{"learn":[3.31407442],"iteration":753,"passed_time":0.8854002982,"remaining_time":0.2888706543},
{"learn":[3.313277779],"iteration":754,"passed_time":0.8861149546,"remaining_time":0.2875472369},
{"learn":[3.311179397],"iteration":755,"passed_time":0.8872589946,"remaining_time":0.2863640141},
{"learn":[3.30966912],"iteration":756,"passed_time":0.8887033425,"remaining_time":0.2852772949},
{"learn":[3.308404177],"iteration":757,"passed_time":0.8903261022,"remaining_time":0.284246592},
{"learn":[3.306874198],"iteration":758,"passed_time":0.8911254952,"remaining_time":0.2829528911},
{"learn":[3.305985345],"iteration":759,"passed_time":0.8917907585,"remaining_time":0.2816181343},
{"learn":[3.304223834],"iteration":760,"passed_time":0.8925484366,"remaining_time":0.2803141608},
{"learn":[3.303945699],"iteration":761,"passed_time":0.893230614,"remaining_time":0.2789880395},
{"learn":[3.301630912],"iteration":762,"passed_time":0.8938951412,"remaining_time":0.2776581238},
{"learn":[3.300412091],"iteration":763,"passed_time":0.894578239,"remaining_time":0.2763356864},
{"learn":[3.300052029],"iteration":764,"passed_time":0.8953003298,"remaining_time":0.2750268987},
{"learn":[3.296641948],"iteration":765,"passed_time":0.8960960167,"remaining_time":0.2737421252},
{"learn":[3.293979722],"iteration":766,"passed_time":0.8968903042,"remaining_time":0.2724582019},
{"learn":[3.292914407],"iteration":767,"passed_time":0.8976774482,"remaining_time":0.2711733958},
{"learn":[3.291250389],"iteration":768,"passed_time":0.8987750159,"remaining_time":0.2699831322},
{"learn":[3.288716251],"iteration":769,"passed_time":0.9108795184,"remaining_time":0.2720808951},
{"learn":[3.287887073],"iteration":770,"passed_time":0.9115853033,"remaining_time":0.2707562055},
{"learn":[3.284360925],"iteration":771,"passed_time":0.9123685918,"remaining_time":0.269456009},
{"learn":[3.281264261],"iteration":772,"passed_time":0.9130975783,"remaining_time":0.2681412035},
{"learn":[3.280515786],"iteration":773,"passed_time":0.913951419,"remaining_time":0.2668643678},
{"learn":[3.279046122],"iteration":774,"passed_time":0.9150968262,"remaining_time":0.2656732721},
{"learn":[3.277731663],"iteration":775,"passed_time":0.9168157692,"remaining_time":0.2646478509},
{"learn":[3.277282323],"iteration":776,"passed_time":0.9175529657,"remaining_time":0.263338882},
{"learn":[3.274739801],"iteration":777,"passed_time":0.9183015234,"remaining_time":0.2620346249},
{"learn":[3.273199772],"iteration":778,"passed_time":0.9189974442,"remaining_time":0.2607168616},
{"learn":[3.272745585],"iteration":779,"passed_time":0.919680422,"remaining_time":0.2593970421},
{"learn":[3.269019223],"iteration":780,"passed_time":0.9203467435,"remaining_time":0.2580741829},
{"learn":[3.268333337],"iteration":781,"passed_time":0.9213329085,"remaining_time":0.2568421663},
{"learn":[3.267796746],"iteration":782,"passed_time":0.9221253894,"remaining_time":0.2555571003},
{"learn":[3.266340276],"iteration":783,"passed_time":0.9227901553,"remaining_time":0.254238104},
{"learn":[3.265984802],"iteration":784,"passed_time":0.9247619467,"remaining_time":0.2532787497},
{"learn":[3.263428053],"iteration":785,"passed_time":0.9263389697,"remaining_time":0.2522093378},
{"learn":[3.261051249],"iteration":786,"passed_time":0.9278973085,"remaining_time":0.251133579},
{"learn":[3.260925947],"iteration":787,"passed_time":0.9294535485,"remaining_time":0.2500560308},
{"learn":[3.25910742],"iteration":788,"passed_time":0.9301627807,"remaining_time":0.2487507563},
{"learn":[3.2567086],"iteration":789,"passed_time":0.9308619545,"remaining_time":0.247444317},
{"learn":[3.255310064],"iteration":790,"passed_time":0.9315954046,"remaining_time":0.2461484697},
{"learn":[3.25291321],"iteration":791,"passed_time":0.9324619933,"remaining_time":0.2448890083},
{"learn":[3.250264261],"iteration":792,"passed_time":0.9332104978,"remaining_time":0.2435997138},
{"learn":[3.24852874],"iteration":793,"passed_time":0.9339873392,"remaining_time":0.2423191333},
{"learn":[3.247310793],"iteration":794,"passed_time":0.9347660036,"remaining_time":0.2410402902},
{"learn":[3.24494745],"iteration":795,"passed_time":0.9355720977,"remaining_time":0.2397697336},
{"learn":[3.24262291],"iteration":796,"passed_time":0.9363046983,"remaining_time":0.2384816233},
{"learn":[3.241497182],"iteration":797,"passed_time":0.937155942,"remaining_time":0.2372249377},
{"learn":[3.238320257],"iteration":798,"passed_time":0.9385792139,"remaining_time":0.236113169},
{"learn":[3.235614404],"iteration":799,"passed_time":0.9399456058,"remaining_time":0.2349864015},
{"learn":[3.233930279],"iteration":800,"passed_time":0.9415493178,"remaining_time":0.2339179953},
{"learn":[3.230607666],"iteration":801,"passed_time":0.9423029929,"remaining_time":0.2326383948},
{"learn":[3.230445798],"iteration":802,"passed_time":0.9430722248,"remaining_time":0.2313639207},
{"learn":[3.228890788],"iteration":803,"passed_time":0.9438321637,"remaining_time":0.2300884379},
{"learn":[3.228116327],"iteration":804,"passed_time":0.9445473654,"remaining_time":0.2288033991},
{"learn":[3.226127365],"iteration":805,"passed_time":0.9453146747,"remaining_time":0.2275323162},
{"learn":[3.225145736],"iteration":806,"passed_time":0.9460574264,"remaining_time":0.2262566088},
{"learn":[3.223195973],"iteration":807,"passed_time":0.9468276805,"remaining_time":0.2249887558},
{"learn":[3.222129909],"iteration":808,"passed_time":0.9475518785,"remaining_time":0.2237112593},
{"learn":[3.220307123],"iteration":809,"passed_time":0.9482864243,"remaining_time":0.2224375563},
{"learn":[3.219541513],"iteration":810,"passed_time":0.9491016449,"remaining_time":0.2211839838},
{"learn":[3.217889473],"iteration":811,"passed_time":0.9502854662,"remaining_time":0.2200168321},
{"learn":[3.215923751],"iteration":812,"passed_time":0.9524072345,"remaining_time":0.2190653787},
{"learn":[3.213704144],"iteration":813,"passed_time":0.9533979914,"remaining_time":0.2178526123},
{"learn":[3.212472893],"iteration":814,"passed_time":0.9549365498,"remaining_time":0.2167647383},
{"learn":[3.209613367],"iteration":815,"passed_time":0.9557365767,"remaining_time":0.2155092281},
{"learn":[3.209500178],"iteration":816,"passed_time":0.9564558277,"remaining_time":0.2142367399},
{"learn":[3.207916511],"iteration":817,"passed_time":0.9571322642,"remaining_time":0.2129560783},
{"learn":[3.206869855],"iteration":818,"passed_time":0.9578535278,"remaining_time":0.2116867992},
{"learn":[3.205866488],"iteration":819,"passed_time":0.9585243505,"remaining_time":0.2104077843},
{"learn":[3.203004216],"iteration":820,"passed_time":0.9592849936,"remaining_time":0.2091498342},
{"learn":[3.201937034],"iteration":821,"passed_time":0.9600796239,"remaining_time":0.2079004538},
{"learn":[3.199456717],"iteration":822,"passed_time":0.9610080043,"remaining_time":0.2066809438},
{"learn":[3.198074936],"iteration":823,"passed_time":0.9623431846,"remaining_time":0.2055490297},
{"learn":[3.197529273],"iteration":824,"passed_time":0.9636519616,"remaining_time":0.2044110222},
{"learn":[3.197094169],"iteration":825,"passed_time":0.9650349321,"remaining_time":0.2032882303},
{"learn":[3.196287238],"iteration":826,"passed_time":0.9658950323,"remaining_time":0.20205543},
{"learn":[3.19624548],"iteration":827,"passed_time":0.9665708342,"remaining_time":0.2007852457},
{"learn":[3.193355396],"iteration":828,"passed_time":0.9673254985,"remaining_time":0.1995327627},
{"learn":[3.192659615],"iteration":829,"passed_time":0.9679975656,"remaining_time":0.1982645616},
{"learn":[3.190365411],"iteration":830,"passed_time":0.9687144949,"remaining_time":0.1970069189},
{"learn":[3.187132738],"iteration":831,"passed_time":0.9694035994,"remaining_time":0.1957449576},
{"learn":[3.183610062],"iteration":832,"passed_time":0.970187585,"remaining_time":0.1945033934},
{"learn":[3.182798994],"iteration":833,"passed_time":0.9708993299,"remaining_time":0.1932485477},
{"learn":[3.181741145],"iteration":834,"passed_time":0.9715875167,"remaining_time":0.1919903476},
{"learn":[3.179812158],"iteration":835,"passed_time":0.9722421051,"remaining_time":0.1907269201},
{"learn":[3.179061446],"iteration":836,"passed_time":0.9731066463,"remaining_time":0.1895058344},
{"learn":[3.17731991],"iteration":837,"passed_time":0.9744610681,"remaining_time":0.188380302},
{"learn":[3.175581534],"iteration":838,"passed_time":0.9760194727,"remaining_time":0.1872933672},
{"learn":[3.175388483],"iteration":839,"passed_time":0.9768160918,"remaining_time":0.186060208},
{"learn":[3.174953221],"iteration":840,"passed_time":0.977568266,"remaining_time":0.1848196841},
{"learn":[3.174137029],"iteration":841,"passed_time":0.9783013627,"remaining_time":0.1835767403},
{"learn":[3.173447694],"iteration":842,"passed_time":0.9790578937,"remaining_time":0.1823393705},
{"learn":[3.172342935],"iteration":843,"passed_time":0.9797265426,"remaining_time":0.1810868965},
{"learn":[3.172091031],"iteration":844,"passed_time":0.9803735238,"remaining_time":0.1798318298},
{"learn":[3.171438159],"iteration":845,"passed_time":0.981036981,"remaining_time":0.1785811998},
{"learn":[3.167822735],"iteration":846,"passed_time":0.9816831633,"remaining_time":0.1773288359},
{"learn":[3.167689245],"iteration":847,"passed_time":0.9822973313,"remaining_time":0.1760721631},
{"learn":[3.16465048],"iteration":848,"passed_time":0.9830681794,"remaining_time":0.1748448705},
{"learn":[3.163444767],"iteration":849,"passed_time":0.9837078824,"remaining_time":0.1735955087},
{"learn":[3.1630161],"iteration":850,"passed_time":0.9844410169,"remaining_time":0.1723639383},
{"learn":[3.160746841],"iteration":851,"passed_time":0.9856830655,"remaining_time":0.171221941},
{"learn":[3.157862755],"iteration":852,"passed_time":0.9871098946,"remaining_time":0.1701115528},
{"learn":[3.156606437],"iteration":853,"passed_time":0.9888040685,"remaining_time":0.1690461288},
{"learn":[3.155836018],"iteration":854,"passed_time":0.9895705126,"remaining_time":0.1678218998},
{"learn":[3.153826837],"iteration":855,"passed_time":0.9903117113,"remaining_time":0.1665944935},
{"learn":[3.152309934],"iteration":856,"passed_time":0.9909888762,"remaining_time":0.1653575371},
{"learn":[3.14949974],"iteration":857,"passed_time":0.9917616745,"remaining_time":0.164137713},
{"learn":[3.148242428],"iteration":858,"passed_time":0.9924707098,"remaining_time":0.1629084634},
{"learn":[3.145520222],"iteration":859,"passed_time":0.9933137997,"remaining_time":0.1617022465},
{"learn":[3.14307712],"iteration":860,"passed_time":0.9941125853,"remaining_time":0.1604897205},
{"learn":[3.142599065],"iteration":861,"passed_time":0.9948690738,"remaining_time":0.159271383},
{"learn":[3.142007917],"iteration":862,"passed_time":0.9956543164,"remaining_time":0.1580586806},
{"learn":[3.139586357],"iteration":863,"passed_time":0.9969073662,"remaining_time":0.1569206039},
{"learn":[3.137313055],"iteration":864,"passed_time":0.9982599343,"remaining_time":0.1557977932},
{"learn":[3.135674522],"iteration":865,"passed_time":1.000197864,"remaining_time":0.1547650275},
{"learn":[3.134977321],"iteration":866,"passed_time":1.001005833,"remaining_time":0.1535568348},
{"learn":[3.132919212],"iteration":867,"passed_time":1.001742945,"remaining_time":0.1523387889},
{"learn":[3.132139292],"iteration":868,"passed_time":1.002582914,"remaining_time":0.1511373553},
{"learn":[3.129230036],"iteration":869,"passed_time":1.003318531,"remaining_time":0.1499211597},
{"learn":[3.128029488],"iteration":870,"passed_time":1.004040718,"remaining_time":0.1487040788},
{"learn":[3.1265664],"iteration":871,"passed_time":1.004686656,"remaining_time":0.1474769403},
{"learn":[3.124980975],"iteration":872,"passed_time":1.005429517,"remaining_time":0.1462652333},
{"learn":[3.123804324],"iteration":873,"passed_time":1.006049229,"remaining_time":0.1450368453},
{"learn":[3.123615276],"iteration":874,"passed_time":1.006472392,"remaining_time":0.1437817703},
{"learn":[3.122116883],"iteration":875,"passed_time":1.00710272,"remaining_time":0.1425579193},
{"learn":[3.121047542],"iteration":876,"passed_time":1.007794588,"remaining_time":0.1413440528},
{"learn":[3.118679639],"iteration":877,"passed_time":1.008833101,"remaining_time":0.1401795425},
{"learn":[3.116614813],"iteration":878,"passed_time":1.00998337,"remaining_time":0.1390307029},
{"learn":[3.115606661],"iteration":879,"passed_time":1.011317811,"remaining_time":0.1379069742},
{"learn":[3.113027533],"iteration":880,"passed_time":1.012225819,"remaining_time":0.1367251674},
{"learn":[3.111238729],"iteration":881,"passed_time":1.013145834,"remaining_time":0.1355455878},
{"learn":[3.10926846],"iteration":882,"passed_time":1.013818251,"remaining_time":0.1343337886},
{"learn":[3.106912393],"iteration":883,"passed_time":1.014475437,"remaining_time":0.1331212112},
{"learn":[3.106096627],"iteration":884,"passed_time":1.015078889,"remaining_time":0.1319029065},
{"learn":[3.102788576],"iteration":885,"passed_time":1.015748812,"remaining_time":0.1306945424},
{"learn":[3.098720449],"iteration":886,"passed_time":1.016487553,"remaining_time":0.1294961595},
{"learn":[3.095749858],"iteration":887,"passed_time":1.017130954,"remaining_time":0.128286787},
{"learn":[3.090921794],"iteration":888,"passed_time":1.017764663,"remaining_time":0.1270774777},
{"learn":[3.09017972],"iteration":889,"passed_time":1.018430703,"remaining_time":0.1258734576},
{"learn":[3.089230376],"iteration":890,"passed_time":1.01915683,"remaining_time":0.1246779961},
{"learn":[3.086993535],"iteration":891,"passed_time":1.020312268,"remaining_time":0.1235355661},
{"learn":[3.086111646],"iteration":892,"passed_time":1.021666403,"remaining_time":0.122416915},
{"learn":[3.084278095],"iteration":893,"passed_time":1.023365519,"remaining_time":0.121338641},
{"learn":[3.083595428],"iteration":894,"passed_time":1.024077905,"remaining_time":0.120143218},
{"learn":[3.08270554],"iteration":895,"passed_time":1.024701729,"remaining_time":0.1189385935},
{"learn":[3.081027244],"iteration":896,"passed_time":1.025346705,"remaining_time":0.117737693},
{"learn":[3.07914713],"iteration":897,"passed_time":1.025986953,"remaining_time":0.1165374935},
{"learn":[3.077451332],"iteration":898,"passed_time":1.026613584,"remaining_time":0.11533701},
{"learn":[3.076403916],"iteration":899,"passed_time":1.027268265,"remaining_time":0.1141409183},
{"learn":[3.076148378],"iteration":900,"passed_time":1.028028688,"remaining_time":0.1129576472},
{"learn":[3.075849596],"iteration":901,"passed_time":1.028677683,"remaining_time":0.1117632073},
{"learn":[3.074802617],"iteration":902,"passed_time":1.029302947,"remaining_time":0.1105674262},
{"learn":[3.074053344],"iteration":903,"passed_time":1.029935453,"remaining_time":0.1093736764},
{"learn":[3.073057415],"iteration":904,"passed_time":1.030542779,"remaining_time":0.1081785238},
{"learn":[3.072159001],"iteration":905,"passed_time":1.031319716,"remaining_time":0.1070022664},
{"learn":[3.0694493],"iteration":906,"passed_time":1.033348963,"remaining_time":0.1059552961},
{"learn":[3.067412778],"iteration":907,"passed_time":1.035502199,"remaining_time":0.104918725},
{"learn":[3.067337434],"iteration":908,"passed_time":1.036368162,"remaining_time":0.1037508281},
{"learn":[3.065565233],"iteration":909,"passed_time":1.037042366,"remaining_time":0.1025646296},
{"learn":[3.065475448],"iteration":910,"passed_time":1.037646797,"remaining_time":0.1013727387},
{"learn":[3.064380463],"iteration":911,"passed_time":1.038286326,"remaining_time":0.1001855227},
{"learn":[3.06171704],"iteration":912,"passed_time":1.03888439,"remaining_time":0.0989955552},
{"learn":[3.059463387],"iteration":913,"passed_time":1.039483988,"remaining_time":0.09780702732},
{"learn":[3.057922581],"iteration":914,"passed_time":1.04029546,"remaining_time":0.09663946893},
{"learn":[3.05567916],"iteration":915,"passed_time":1.040934739,"remaining_time":0.0954568975},
{"learn":[3.053911811],"iteration":916,"passed_time":1.04159065,"remaining_time":0.09427701633},
{"learn":[3.052981662],"iteration":917,"passed_time":1.042179544,"remaining_time":0.09309229039},
{"learn":[3.05105643],"iteration":918,"passed_time":1.042835061,"remaining_time":0.09191473336},
{"learn":[3.050604957],"iteration":919,"passed_time":1.043480327,"remaining_time":0.09073741971},
{"learn":[3.048744644],"iteration":920,"passed_time":1.044214504,"remaining_time":0.08956888794},
{"learn":[3.048077381],"iteration":921,"passed_time":1.045381987,"remaining_time":0.08843795551},
{"learn":[3.047038199],"iteration":922,"passed_time":1.04711829,"remaining_time":0.08735439687},
{"learn":[3.046593866],"iteration":923,"passed_time":1.0477829,"remaining_time":0.0861812775},
{"learn":[3.046465224],"iteration":924,"passed_time":1.048471061,"remaining_time":0.0850111671},
{"learn":[3.044546346],"iteration":925,"passed_time":1.049117086,"remaining_time":0.0838387304},
{"learn":[3.04343095],"iteration":926,"passed_time":1.049762131,"remaining_time":0.08266735225},
{"learn":[3.04149626],"iteration":927,"passed_time":1.050432789,"remaining_time":0.08149909567},
{"learn":[3.037529616],"iteration":928,"passed_time":1.051125123,"remaining_time":0.080333567},
{"learn":[3.03740565],"iteration":929,"passed_time":1.051839204,"remaining_time":0.07917069274},
{"learn":[3.036617338],"iteration":930,"passed_time":1.052446242,"remaining_time":0.07800084929},
{"learn":[3.035832879],"iteration":931,"passed_time":1.053036547,"remaining_time":0.07683099272},
{"learn":[3.034787441],"iteration":932,"passed_time":1.053716536,"remaining_time":0.07566881876},
{"learn":[3.034523539],"iteration":933,"passed_time":1.054442337,"remaining_time":0.07451091464},
{"learn":[3.033275286],"iteration":934,"passed_time":1.055131832,"remaining_time":0.07335141077},
{"learn":[3.031925679],"iteration":935,"passed_time":1.056065161,"remaining_time":0.07220958364},
{"learn":[3.029463505],"iteration":936,"passed_time":1.057256893,"remaining_time":0.07108557554},
{"learn":[3.028366251],"iteration":937,"passed_time":1.058795493,"remaining_time":0.06998435029},
{"learn":[3.02634163],"iteration":938,"passed_time":1.060136016,"remaining_time":0.06886932583},
{"learn":[3.025057253],"iteration":939,"passed_time":1.060835028,"remaining_time":0.06771287414},
{"learn":[3.023632925],"iteration":940,"passed_time":1.061456763,"remaining_time":0.06655254945},
{"learn":[3.023406279],"iteration":941,"passed_time":1.062099181,"remaining_time":0.06539464171},
{"learn":[3.021978527],"iteration":942,"passed_time":1.062963144,"remaining_time":0.0642512187},
{"learn":[3.020767467],"iteration":943,"passed_time":1.06367425,"remaining_time":0.06309931993},
{"learn":[3.020409137],"iteration":944,"passed_time":1.064302152,"remaining_time":0.06194351147},
{"learn":[3.019172339],"iteration":945,"passed_time":1.064959996,"remaining_time":0.06079052834},
{"learn":[3.016330482],"iteration":946,"passed_time":1.065609657,"remaining_time":0.05963813289},
{"learn":[3.015748298],"iteration":947,"passed_time":1.0662158,"remaining_time":0.05848441099},
{"learn":[3.015116738],"iteration":948,"passed_time":1.066840467,"remaining_time":0.05733283857},
{"learn":[3.014158081],"iteration":949,"passed_time":1.067540068,"remaining_time":0.05618631936},
{"learn":[3.012875966],"iteration":950,"passed_time":1.068331495,"remaining_time":0.05504547136},
{"learn":[3.01253724],"iteration":951,"passed_time":1.070290926,"remaining_time":0.05396424839},
{"learn":[3.011034855],"iteration":952,"passed_time":1.071408674,"remaining_time":0.05283967226},
{"learn":[3.010103724],"iteration":953,"passed_time":1.072933718,"remaining_time":0.05173474952},
{"learn":[3.008661175],"iteration":954,"passed_time":1.073619935,"remaining_time":0.050589421},
{"learn":[3.006728832],"iteration":955,"passed_time":1.074307703,"remaining_time":0.04944512441},
{"learn":[3.005753013],"iteration":956,"passed_time":1.07501339,"remaining_time":0.04830258703},
{"learn":[3.004267747],"iteration":957,"passed_time":1.075725364,"remaining_time":0.04716123725},
{"learn":[3.003513795],"iteration":958,"passed_time":1.076445532,"remaining_time":0.04602113327},
{"learn":[3.002697009],"iteration":959,"passed_time":1.077141839,"remaining_time":0.04488090996},
{"learn":[3.001978024],"iteration":960,"passed_time":1.077790989,"remaining_time":0.04373969673},
{"learn":[3.000904747],"iteration":961,"passed_time":1.078434987,"remaining_time":0.04259930302},
{"learn":[2.999711143],"iteration":962,"passed_time":1.079144966,"remaining_time":0.04146247531},
{"learn":[2.99848128],"iteration":963,"passed_time":1.079772701,"remaining_time":0.04032346185},
{"learn":[2.997475643],"iteration":964,"passed_time":1.080548359,"remaining_time":0.03919087311},
{"learn":[2.994876782],"iteration":965,"passed_time":1.081888901,"remaining_time":0.03807890541},
{"learn":[2.994615864],"iteration":966,"passed_time":1.08323172,"remaining_time":0.03696654268},
{"learn":[2.994401528],"iteration":967,"passed_time":1.084489857,"remaining_time":0.03585090435},
{"learn":[2.991511685],"iteration":968,"passed_time":1.085557837,"remaining_time":0.0347288885},
{"learn":[2.988879166],"iteration":969,"passed_time":1.086221211,"remaining_time":0.03359447045},
{"learn":[2.988672193],"iteration":970,"passed_time":1.08689511,"remaining_time":0.03246133697},
{"learn":[2.988122572],"iteration":971,"passed_time":1.0876996,"remaining_time":0.03133291029},
{"learn":[2.987005875],"iteration":972,"passed_time":1.088410929,"remaining_time":0.03020256431},
{"learn":[2.984082154],"iteration":973,"passed_time":1.089079698,"remaining_time":0.02907194266},
{"learn":[2.982041491],"iteration":974,"passed_time":1.089725553,"remaining_time":0.02794168085},
{"learn":[2.981273785],"iteration":975,"passed_time":1.0903869,"remaining_time":0.02681279262},
{"learn":[2.980680548],"iteration":976,"passed_time":1.091062726,"remaining_time":0.02568520236},
{"learn":[2.978582525],"iteration":977,"passed_time":1.091717634,"remaining_time":0.02455806539},
{"learn":[2.977118046],"iteration":978,"passed_time":1.09246465,"remaining_time":0.0234338689},
{"learn":[2.975759242],"iteration":979,"passed_time":1.093503711,"remaining_time":0.02231640227},
{"learn":[2.974540445],"iteration":980,"passed_time":1.094998467,"remaining_time":0.02120792138},
{"learn":[2.973086014],"iteration":981,"passed_time":1.096075434,"remaining_time":0.02009099574},
{"learn":[2.970800821],"iteration":982,"passed_time":1.097397214,"remaining_time":0.01897838519},
{"learn":[2.968734574],"iteration":983,"passed_time":1.098101007,"remaining_time":0.01785530093},
{"learn":[2.967332707],"iteration":984,"passed_time":1.098985748,"remaining_time":0.01673582357},
{"learn":[2.965758086],"iteration":985,"passed_time":1.099751143,"remaining_time":0.01561512779},
{"learn":[2.964626403],"iteration":986,"passed_time":1.100397098,"remaining_time":0.0144935788},
{"learn":[2.96229236],"iteration":987,"passed_time":1.101010228,"remaining_time":0.01337259386},
{"learn":[2.961381098],"iteration":988,"passed_time":1.101718165,"remaining_time":0.01225369041},
{"learn":[2.959420967],"iteration":989,"passed_time":1.102365446,"remaining_time":0.0111350045},
{"learn":[2.956460371],"iteration":990,"passed_time":1.102974045,"remaining_time":0.01001691868},
{"learn":[2.954260489],"iteration":991,"passed_time":1.103621667,"remaining_time":0.00890017473},
{"learn":[2.953177903],"iteration":992,"passed_time":1.104259086,"remaining_time":0.007784303727},
{"learn":[2.951266627],"iteration":993,"passed_time":1.104980967,"remaining_time":0.006669905232},
{"learn":[2.94948014],"iteration":994,"passed_time":1.106003903,"remaining_time":0.005557808558},
{"learn":[2.949419118],"iteration":995,"passed_time":1.107191058,"remaining_time":0.004446550432},
{"learn":[2.948342573],"iteration":996,"passed_time":1.108319173,"remaining_time":0.003334962408},
{"learn":[2.947249577],"iteration":997,"passed_time":1.109548974,"remaining_time":0.002223545039},
{"learn":[2.94392393],"iteration":998,"passed_time":1.110224951,"remaining_time":0.001111336287},
{"learn":[2.943018472],"iteration":999,"passed_time":1.110894069,"remaining_time":0}
]}